{
"id": "70",
"surah": 70,
"name": "Al-Ma'arij",
"nameAr": "المعارج",
"revelation": "makkah",
"ayahCount": 44,
"words": [
"سَأَلَ سَآئِلٌۢ",
"بِعَذَابٍۢ وَاقِعٍۢ",
"لِّلْكَـٰفِرِينَ",
"لَيْسَ",
"لَهُۥ",
"دَافِعٌۭ",
"مِّنَ",
"ٱللَّهِ",
"ذِى",
"ٱلْمَعَارِجِ",
"تَعْرُجُ",
"ٱلْمَلَـٰٓئِكَةُ",
"وَٱلرُّوحُ",
"إِلَيْهِ",
"فِى",
"يَوْمٍۢ كَانَ",
"مِقْدَارُهُۥ",
"خَمْسِينَ",
"أَلْفَ",
"سَنَةٍۢ",
"فَٱصْبِرْ",
"صَبْرًۭا جَمِيلًا",
"إِنَّهُمْ",
"يَرَوْنَهُۥ",
"بَعِيدًۭا",
"وَنَرَىٰهُ",
"قَرِيبًۭا",
"يَوْمَ",
"تَكُونُ",
"ٱلسَّمَآءُ",
"كَٱلْمُهْلِ",
"وَتَكُونُ",
"ٱلْجِبَالُ",
"كَٱلْعِهْنِ",
"وَلَا",
"يَسْـَٔلُ",
"حَمِيمٌ",
"حَمِيمًۭا",
"يُبَصَّرُونَهُمْ",
"يَوَدُّ",
"ٱلْمُجْرِمُ",
"لَوْ",
"يَفْتَدِى",
"مِنْ",
"عَذَابِ",
"يَوْمِئِذٍۭ بِبَنِيهِ",
"وَصَـٰحِبَتِهِۦ",
"وَأَخِيهِ",
"وَفَصِيلَتِهِ",
"ٱلَّتِى",
"تُـْٔوِيهِ",
"وَمَن فِى",
"ٱلْأَرْضِ",
"جَمِيعًۭا ثُمَّ",
"يُنجِيهِ",
"كَلَّآ",
"إِنَّهَا",
"لَظَىٰ",
"نَزَّاعَةًۭ لِّلشَّوَىٰ",
"تَدْعُوا۟",
"مَنْ",
"أَدْبَرَ",
"وَتَوَلَّىٰ",
"وَجَمَعَ",
"فَأَوْعَىٰٓ",
"إِنَّ",
"ٱلْإِنسَـٰنَ",
"خُلِقَ",
"هَلُوعًا",
"إِذَا",
"مَسَّهُ",
"ٱلشَّرُّ",
"جَزُوعًۭا",
"وَإِذَا",
"مَسَّهُ",
"ٱلْخَيْرُ",
"مَنُوعًا",
"إِلَّا",
"ٱلْمُصَلِّينَ",
"ٱلَّذِينَ",
"هُمْ",
"عَلَىٰ",
"صَلَاتِهِمْ",
"دَآئِمُونَ",
"وَٱلَّذِينَ",
"فِىٓ",
"أَمْوَٰلِهِمْ",
"حَقٌّۭ مَّعْلُومٌۭ",
"لِّلسَّآئِلِ",
"وَٱلْمَحْرُومِ",
"وَٱلَّذِينَ",
"يُصَدِّقُونَ",
"بِيَوْمِ",
"ٱلدِّينِ",
"وَٱلَّذِينَ",
"هُم مِّنْ",
"عَذَابِ",
"رَبِّهِم مُّشْفِقُونَ",
"إِنَّ",
"عَذَابَ",
"رَبِّهِمْ",
"غَيْرُ",
"مَأْمُونٍۢ",
"وَٱلَّذِينَ",
"هُمْ",
"لِفُرُوجِهِمْ",
"حَـٰفِظُونَ",
"إِلَّا",
"عَلَىٰٓ",
"أَزْوَٰجِهِمْ",
"أَوْ",
"مَا",
"مَلَكَتْ",
"أَيْمَـٰنُهُمْ",
"فَإِنَّهُمْ",
"غَيْرُ",
"مَلُومِينَ",
"فَمَنِ",
"ٱبْتَغَىٰ",
"وَرَآءَ",
"ذَٰلِكَ",
"فَأُو۟لَـٰٓئِكَ",
"هُمُ",
"ٱلْعَادُونَ",
"وَٱلَّذِينَ",
"هُمْ",
"لِأَمَـٰنَـٰتِهِمْ",
"وَعَهْدِهِمْ",
"رَٰعُونَ",
"وَٱلَّذِينَ",
"هُم بِشَهَـٰدَٰتِهِمْ",
"قَآئِمُونَ",
"وَٱلَّذِينَ",
"هُمْ",
"عَلَىٰ",
"صَلَاتِهِمْ",
"يُحَافِظُونَ",
"أُو۟لَـٰٓئِكَ",
"فِى",
"جَنَّـٰتٍۢ مُّكْرَمُونَ",
"فَمَالِ",
"ٱلَّذِينَ",
"كَفَرُوا۟",
"قِبَلَكَ",
"مُهْطِعِينَ",
"عَنِ",
"ٱلْيَمِينِ",
"وَعَنِ",
"ٱلشِّمَالِ",
"عِزِينَ",
"أَيَطْمَعُ",
"كُلُّ",
"ٱمْرِئٍۢ مِّنْهُمْ",
"أَن يُدْخَلَ",
"جَنَّةَ",
"نَعِيمٍۢ",
"كَلَّآ",
"إِنَّا",
"خَلَقْنَـٰهُم مِّمَّا",
"يَعْلَمُونَ",
"فَلَآ",
"أُقْسِمُ",
"بِرَبِّ",
"ٱلْمَشَـٰرِقِ",
"وَٱلْمَغَـٰرِبِ",
"إِنَّا",
"لَقَـٰدِرُونَ",
"عَلَىٰٓ أَن",
"نُّبَدِّلَ",
"خَيْرًۭا مِّنْهُمْ",
"وَمَا",
"نَحْنُ",
"بِمَسْبُوقِينَ",
"فَذَرْهُمْ",
"يَخُوضُوا۟",
"وَيَلْعَبُوا۟",
"حَتَّىٰ",
"يُلَـٰقُوا۟",
"يَوْمَهُمُ",
"ٱلَّذِى",
"يُوعَدُونَ",
"يَوْمَ",
"يَخْرُجُونَ",
"مِنَ",
"ٱلْأَجْدَاثِ",
"سِرَاعًۭا كَأَنَّهُمْ",
"إِلَىٰ",
"نُصُبٍۢ يُوفِضُونَ",
"خَـٰشِعَةً",
"أَبْصَـٰرُهُمْ",
"تَرْهَقُهُمْ",
"ذِلَّةٌۭ ذَٰلِكَ",
"ٱلْيَوْمُ",
"ٱلَّذِى",
"كَانُوا۟",
"يُوعَدُونَ"
],
"phonemes": [
"سَ",
"ءَ",
"لَ",
"سَ",
"اااا",
"ءِ",
"لُ",
"۾۾۾",
"بِ",
"عَ",
"ذَ",
"اا",
"بِ",
"وووَ",
"اا",
"قِ",
"ع",
"لِ",
"ل",
"كَ",
"اا",
"فِ",
"رِ",
"ۦۦ",
"نَ",
"لَ",
"ي",
"سَ",
"لَ",
"هُ",
"ۥۥ",
"دَ",
"اا",
"فِ",
"ع",
"مِ",
"نَ",
"للَ",
"اا",
"هِ",
"ذِ",
"ل",
"مَ",
"عَ",
"اا",
"رِ",
"جڇ",
"تَ",
"ع",
"رُ",
"جُ",
"ل",
"مَ",
"لَ",
"اااا",
"ءِ",
"كَ",
"تُ",
"وَ",
"ررُ",
"ۥۥ",
"حُ",
"ءِ",
"لَ",
"ي",
"هِ",
"فِ",
"ۦۦ",
"يَ",
"و",
"مِ",
"ںںں",
"كَ",
"اا",
"نَ",
"مِ",
"قڇ",
"دَ",
"اا",
"رُ",
"هُ",
"ۥۥ",
"خَ",
"م",
"سِ",
"ۦۦ",
"نَ",
"ءَ",
"ل",
"فَ",
"سَ",
"نَ",
"ه",
"فَ",
"ص",
"بِ",
"ر",
"صَ",
"بڇ",
"رَ",
"ںںں",
"جَ",
"مِ",
"ۦۦ",
"لَ",
"اا",
"ءِ",
"ننننَ",
"هُ",
"م",
"يَ",
"رَ",
"و",
"نَ",
"هُ",
"ۥۥ",
"بَ",
"عِ",
"ۦۦ",
"دَ",
"اا",
"وَ",
"نَ",
"رَ",
"اا",
"هُ",
"قَ",
"رِ",
"ۦۦ",
"بَ",
"اا",
"يَ",
"و",
"مَ",
"تَ",
"كُ",
"ۥۥ",
"نُ",
"سسَ",
"مَ",
"اااا",
"ءُ",
"كَ",
"ل",
"مُ",
"ه",
"ل",
"وَ",
"تَ",
"كُ",
"ۥۥ",
"نُ",
"ل",
"جِ",
"بَ",
"اا",
"لُ",
"كَ",
"ل",
"عِ",
"ه",
"ن",
"وَ",
"لَ",
"اا",
"يَ",
"س",
"ءَ",
"لُ",
"حَ",
"مِ",
"ۦۦ",
"مُ",
"ن",
"حَ",
"مِ",
"ۦۦ",
"مَ",
"اا",
"يُ",
"بَ",
"صصَ",
"رُ",
"ۥۥ",
"نَ",
"هُ",
"م",
"يَ",
"وَ",
"ددُ",
"ل",
"مُ",
"جڇ",
"رِ",
"مُ",
"لَ",
"و",
"يَ",
"ف",
"تَ",
"دِ",
"ۦۦ",
"مِ",
"ن",
"عَ",
"ذَ",
"اا",
"بِ",
"يَ",
"و",
"مِ",
"ءِ",
"ذِ",
"۾۾۾",
"بِ",
"بَ",
"نِ",
"ۦۦۦۦ",
"ه",
"وَ",
"صَ",
"اا",
"حِ",
"بَ",
"تِ",
"هِ",
"ۦۦ",
"وَ",
"ءَ",
"خِ",
"ۦۦۦۦ",
"ه",
"وَ",
"فَ",
"صِ",
"ۦۦ",
"لَ",
"تِ",
"هِ",
"للَ",
"تِ",
"ۦۦ",
"تُ",
"ء",
"وِ",
"ۦۦۦۦ",
"ه",
"وَ",
"مَ",
"ںںں",
"فِ",
"ل",
"ءَ",
"ر",
"ضِ",
"جَ",
"مِ",
"ۦۦ",
"عَ",
"ںںں",
"ثُ",
"ممممَ",
"يُ",
"ںںں",
"جِ",
"ۦۦۦۦ",
"ه",
"كَ",
"للَ",
"اااا",
"ءِ",
"ننننَ",
"هَ",
"اا",
"لَ",
"ظَ",
"اا",
"نَ",
"ززَ",
"اا",
"عَ",
"تَ",
"للِ",
"ششَ",
"وَ",
"اا",
"تَ",
"دڇ",
"عُ",
"ۥۥ",
"مَ",
"ن",
"ءَ",
"دڇ",
"بَ",
"رَ",
"وَ",
"تَ",
"وَ",
"للَ",
"اا",
"وَ",
"جَ",
"مَ",
"عَ",
"فَ",
"ءَ",
"و",
"عَ",
"اا",
"ءِ",
"ننننَ",
"ل",
"ءِ",
"ںںں",
"سَ",
"اا",
"نَ",
"خُ",
"لِ",
"قَ",
"هَ",
"لُ",
"ۥۥ",
"عَ",
"اا",
"ءِ",
"ذَ",
"اا",
"مَ",
"سسَ",
"هُ",
"ششَ",
"ررُ",
"جَ",
"زُ",
"ۥۥ",
"عَ",
"اا",
"وَ",
"ءِ",
"ذَ",
"اا",
"مَ",
"سسَ",
"هُ",
"ل",
"خَ",
"ي",
"رُ",
"مَ",
"نُ",
"ۥۥ",
"عَ",
"اا",
"ءِ",
"للَ",
"ل",
"مُ",
"صَ",
"للِ",
"ۦۦۦۦ",
"ن",
"ءَ",
"للَ",
"ذِ",
"ۦۦ",
"نَ",
"هُ",
"م",
"عَ",
"لَ",
"اا",
"صَ",
"لَ",
"اا",
"تِ",
"هِ",
"م",
"دَ",
"اااا",
"ءِ",
"مُ",
"ۥۥۥۥ",
"ن",
"وَ",
"للَ",
"ذِ",
"ۦۦ",
"نَ",
"فِ",
"ۦۦۦۦ",
"ءَ",
"م",
"وَ",
"اا",
"لِ",
"هِ",
"م",
"حَ",
"ققُ",
"ممممَ",
"ع",
"لُ",
"ۥۥۥۥ",
"م",
"لِ",
"سسَ",
"اااا",
"ءِ",
"لِ",
"وَ",
"ل",
"مَ",
"ح",
"رُ",
"ۥۥۥۥ",
"م",
"وَ",
"للَ",
"ذِ",
"ۦۦ",
"نَ",
"يُ",
"صَ",
"ددِ",
"قُ",
"ۥۥ",
"نَ",
"بِ",
"يَ",
"و",
"مِ",
"ددِ",
"ۦۦۦۦ",
"ن",
"وَ",
"للَ",
"ذِ",
"ۦۦ",
"نَ",
"هُ",
"ممممِ",
"ن",
"عَ",
"ذَ",
"اا",
"بِ",
"رَ",
"ببِ",
"هِ",
"ممممُ",
"ش",
"فِ",
"قُ",
"ۥۥۥۥ",
"ن",
"ءِ",
"ننننَ",
"عَ",
"ذَ",
"اا",
"بَ",
"رَ",
"ببِ",
"هِ",
"م",
"غَ",
"ي",
"رُ",
"مَ",
"ء",
"مُ",
"ۥۥۥۥ",
"ن",
"وَ",
"للَ",
"ذِ",
"ۦۦ",
"نَ",
"هُ",
"م",
"لِ",
"فُ",
"رُ",
"ۥۥ",
"جِ",
"هِ",
"م",
"حَ",
"اا",
"فِ",
"ظُ",
"ۥۥۥۥ",
"ن",
"ءِ",
"للَ",
"اا",
"عَ",
"لَ",
"اااا",
"ءَ",
"ز",
"وَ",
"اا",
"جِ",
"هِ",
"م",
"ءَ",
"و",
"مَ",
"اا",
"مَ",
"لَ",
"كَ",
"ت",
"ءَ",
"ي",
"مَ",
"اا",
"نُ",
"هُ",
"م",
"فَ",
"ءِ",
"ننننَ",
"هُ",
"م",
"غَ",
"ي",
"رُ",
"مَ",
"لُ",
"ۥۥ",
"مِ",
"ۦۦۦۦ",
"ن",
"فَ",
"مَ",
"نِ",
"بڇ",
"تَ",
"غَ",
"اا",
"وَ",
"رَ",
"اااا",
"ءَ",
"ذَ",
"اا",
"لِ",
"كَ",
"فَ",
"ءُ",
"لَ",
"اااا",
"ءِ",
"كَ",
"هُ",
"مُ",
"ل",
"عَ",
"اا",
"دُ",
"ۥۥۥۥ",
"ن",
"وَ",
"للَ",
"ذِ",
"ۦۦ",
"نَ",
"هُ",
"م",
"لِ",
"ءَ",
"مَ",
"اا",
"نَ",
"اا",
"تِ",
"هِ",
"م",
"وَ",
"عَ",
"ه",
"دِ",
"هِ",
"م",
"رَ",
"اا",
"عُ",
"ۥۥۥۥ",
"ن",
"وَ",
"للَ",
"ذِ",
"ۦۦ",
"نَ",
"هُ",
"۾۾۾",
"بِ",
"شَ",
"هَ",
"اا",
"دَ",
"اا",
"تِ",
"هِ",
"م",
"قَ",
"اااا",
"ءِ",
"مُ",
"ۥۥۥۥ",
"ن",
"وَ",
"للَ",
"ذِ",
"ۦۦ",
"نَ",
"هُ",
"م",
"عَ",
"لَ",
"اا",
"صَ",
"لَ",
"اا",
"تِ",
"هِ",
"م",
"يُ",
"حَ",
"اا",
"فِ",
"ظُ",
"ۥۥۥۥ",
"ن",
"ءُ",
"لَ",
"اااا",
"ءِ",
"كَ",
"فِ",
"ۦۦ",
"جَ",
"ننننَ",
"اا",
"تِ",
"ممممُ",
"ك",
"رَ",
"مُ",
"ۥۥۥۥ",
"ن",
"فَ",
"مَ",
"اا",
"لِ",
"للَ",
"ذِ",
"ۦۦ",
"نَ",
"كَ",
"فَ",
"رُ",
"ۥۥ",
"قِ",
"بَ",
"لَ",
"كَ",
"مُ",
"ه",
"طِ",
"عِ",
"ۦۦۦۦ",
"ن",
"عَ",
"نِ",
"ل",
"يَ",
"مِ",
"ۦۦ",
"نِ",
"وَ",
"عَ",
"نِ",
"ششِ",
"مَ",
"اا",
"لِ",
"عِ",
"زِ",
"ۦۦۦۦ",
"ن",
"ءَ",
"يَ",
"طڇ",
"مَ",
"عُ",
"كُ",
"للُ",
"م",
"رِ",
"ءِ",
"ممممِ",
"ن",
"هُ",
"م",
"ءَ",
"يييُ",
"دڇ",
"خَ",
"لَ",
"جَ",
"ننننَ",
"تَ",
"نَ",
"عِ",
"ۦۦۦۦ",
"م",
"كَ",
"للَ",
"اااا",
"ءِ",
"ننننَ",
"اا",
"خَ",
"لَ",
"قڇ",
"نَ",
"اا",
"هُ",
"ممممِ",
"ممممَ",
"اا",
"يَ",
"ع",
"لَ",
"مُ",
"ۥۥۥۥ",
"ن",
"فَ",
"لَ",
"اااا",
"ءُ",
"قڇ",
"سِ",
"مُ",
"بِ",
"رَ",
"ببِ",
"ل",
"مَ",
"شَ",
"اا",
"رِ",
"قِ",
"وَ",
"ل",
"مَ",
"غَ",
"اا",
"رِ",
"بِ",
"ءِ",
"ننننَ",
"اا",
"لَ",
"قَ",
"اا",
"دِ",
"رُ",
"ۥۥۥۥ",
"ن",
"عَ",
"لَ",
"اااا",
"ءَ",
"ننننُ",
"بَ",
"ددِ",
"لَ",
"خَ",
"ي",
"رَ",
"ممممِ",
"ن",
"هُ",
"م",
"وَ",
"مَ",
"اا",
"نَ",
"ح",
"نُ",
"بِ",
"مَ",
"س",
"بُ",
"ۥۥ",
"قِ",
"ۦۦۦۦ",
"ن",
"فَ",
"ذَ",
"ر",
"هُ",
"م",
"يَ",
"خُ",
"ۥۥ",
"ضُ",
"ۥۥ",
"وَ",
"يَ",
"ل",
"عَ",
"بُ",
"ۥۥ",
"حَ",
"تتَ",
"اا",
"يُ",
"لَ",
"اا",
"قُ",
"ۥۥ",
"يَ",
"و",
"مَ",
"هُ",
"مُ",
"للَ",
"ذِ",
"ۦۦ",
"يُ",
"ۥۥ",
"عَ",
"دُ",
"ۥۥۥۥ",
"ن",
"يَ",
"و",
"مَ",
"يَ",
"خ",
"رُ",
"جُ",
"ۥۥ",
"نَ",
"مِ",
"نَ",
"ل",
"ءَ",
"جڇ",
"دَ",
"اا",
"ثِ",
"سِ",
"رَ",
"اا",
"عَ",
"ںںں",
"كَ",
"ءَ",
"ننننَ",
"هُ",
"م",
"ءِ",
"لَ",
"اا",
"نُ",
"صُ",
"بِ",
"يييُ",
"ۥۥ",
"فِ",
"ضُ",
"ۥۥۥۥ",
"ن",
"خَ",
"اا",
"شِ",
"عَ",
"تَ",
"ن",
"ءَ",
"بڇ",
"صَ",
"اا",
"رُ",
"هُ",
"م",
"تَ",
"ر",
"هَ",
"قُ",
"هُ",
"م",
"ذِ",
"للَ",
"تُ",
"ںںں",
"ذَ",
"اا",
"لِ",
"كَ",
"ل",
"يَ",
"و",
"مُ",
"للَ",
"ذِ",
"ۦۦ",
"كَ",
"اا",
"نُ",
"ۥۥ",
"يُ",
"ۥۥ",
"عَ",
"دُ",
"ۥۥۥۥ",
"ن"
],
"phonemeToWord": [
0,
0,
0,
1,
1,
1,
1,
1,
1,
1,
1,
1,
1,
1,
1,
1,
1,
2,
2,
2,
2,
2,
2,
2,
2,
3,
3,
3,
4,
4,
4,
5,
5,
5,
5,
6,
6,
7,
7,
7,
8,
9,
9,
9,
9,
9,
9,
10,
10,
10,
10,
11,
11,
11,
11,
11,
11,
11,
12,
12,
12,
12,
13,
13,
13,
13,
14,
14,
15,
15,
15,
15,
15,
15,
15,
16,
16,
16,
16,
16,
16,
16,
17,
17,
17,
17,
17,
18,
18,
18,
19,
19,
19,
20,
20,
20,
20,
21,
21,
21,
21,
21,
21,
21,
21,
21,
22,
22,
22,
22,
23,
23,
23,
23,
23,
23,
24,
24,
24,
24,
24,
25,
25,
25,
25,
25,
26,
26,
26,
26,
26,
27,
27,
27,
28,
28,
28,
28,
29,
29,
29,
29,
30,
30,
30,
30,
30,
31,
31,
31,
31,
31,
32,
32,
32,
32,
32,
33,
33,
33,
33,
33,
34,
34,
34,
35,
35,
35,
35,
36,
36,
36,
36,
36,
37,
37,
37,
37,
37,
38,
38,
38,
38,
38,
38,
38,
38,
39,
39,
39,
40,
40,
40,
40,
40,
41,
41,
42,
42,
42,
42,
42,
43,
43,
44,
44,
44,
44,
45,
45,
45,
45,
45,
45,
45,
45,
45,
45,
45,
46,
46,
46,
46,
46,
46,
46,
46,
47,
47,
47,
47,
47,
48,
48,
48,
48,
48,
48,
48,
49,
49,
49,
50,
50,
50,
50,
50,
51,
51,
51,
51,
52,
52,
52,
52,
53,
53,
53,
53,
53,
53,
53,
54,
54,
54,
54,
54,
55,
55,
55,
56,
56,
56,
56,
57,
57,
57,
58,
58,
58,
58,
58,
58,
58,
58,
58,
59,
59,
59,
59,
60,
60,
61,
61,
61,
61,
62,
62,
62,
62,
62,
63,
63,
63,
63,
64,
64,
64,
64,
64,
65,
65,
66,
66,
66,
66,
66,
66,
67,
67,
67,
68,
68,
68,
68,
68,
69,
69,
69,
70,
70,
70,
71,
71,
72,
72,
72,
72,
72,
73,
73,
73,
73,
74,
74,
74,
75,
75,
75,
75,
76,
76,
76,
76,
76,
77,
77,
78,
78,
78,
78,
78,
78,
79,
79,
79,
79,
79,
80,
80,
81,
81,
81,
82,
82,
82,
82,
82,
82,
83,
83,
83,
83,
83,
83,
84,
84,
84,
84,
84,
85,
85,
86,
86,
86,
86,
86,
86,
86,
87,
87,
87,
87,
87,
87,
87,
88,
88,
88,
88,
88,
89,
89,
89,
89,
89,
89,
89,
90,
90,
90,
90,
90,
91,
91,
91,
91,
91,
91,
92,
92,
92,
92,
93,
93,
93,
94,
94,
94,
94,
94,
95,
95,
95,
96,
96,
96,
96,
97,
97,
97,
97,
97,
97,
97,
97,
97,
98,
98,
99,
99,
99,
99,
100,
100,
100,
100,
101,
101,
101,
102,
102,
102,
102,
102,
103,
103,
103,
103,
103,
104,
104,
105,
105,
105,
105,
105,
105,
105,
106,
106,
106,
106,
106,
106,
107,
107,
107,
108,
108,
108,
109,
109,
109,
109,
109,
109,
109,
110,
110,
111,
111,
112,
112,
112,
112,
113,
113,
113,
113,
113,
113,
113,
114,
114,
114,
114,
114,
115,
115,
115,
116,
116,
116,
116,
116,
116,
117,
117,
117,
118,
118,
118,
118,
119,
119,
119,
119,
120,
120,
120,
120,
121,
121,
121,
121,
121,
121,
122,
122,
123,
123,
123,
123,
123,
123,
124,
124,
124,
124,
124,
125,
125,
126,
126,
126,
126,
126,
126,
126,
126,
126,
127,
127,
127,
127,
127,
127,
128,
128,
128,
128,
128,
129,
129,
129,
129,
129,
130,
130,
130,
130,
130,
130,
130,
130,
130,
130,
130,
131,
131,
131,
131,
131,
131,
132,
132,
132,
132,
132,
133,
133,
134,
134,
134,
135,
135,
135,
135,
135,
135,
136,
136,
136,
136,
136,
136,
136,
137,
137,
137,
137,
137,
138,
138,
139,
139,
139,
139,
139,
139,
139,
139,
139,
139,
140,
140,
140,
140,
141,
141,
141,
141,
142,
142,
142,
142,
143,
143,
143,
143,
144,
144,
144,
144,
144,
144,
145,
145,
146,
146,
146,
146,
146,
147,
147,
147,
148,
148,
148,
148,
149,
149,
149,
149,
150,
150,
150,
150,
150,
151,
151,
152,
152,
152,
152,
152,
152,
152,
153,
153,
153,
153,
153,
154,
154,
154,
155,
155,
155,
155,
156,
156,
156,
157,
157,
157,
158,
158,
158,
158,
158,
158,
158,
158,
158,
159,
159,
159,
159,
159,
159,
160,
160,
160,
161,
161,
161,
161,
162,
162,
162,
163,
163,
163,
163,
163,
163,
164,
164,
164,
164,
164,
164,
164,
165,
165,
165,
166,
166,
166,
166,
166,
166,
166,
167,
167,
167,
168,
168,
168,
168,
168,
169,
169,
169,
169,
169,
169,
169,
170,
170,
170,
171,
171,
171,
172,
172,
172,
172,
172,
172,
172,
172,
173,
173,
173,
173,
173,
174,
174,
174,
174,
174,
175,
175,
175,
175,
175,
175,
176,
176,
176,
177,
177,
177,
177,
177,
178,
178,
178,
178,
178,
179,
179,
179,
180,
180,
180,
180,
180,
180,
181,
181,
181,
182,
182,
182,
182,
182,
182,
183,
183,
184,
184,
184,
184,
184,
184,
185,
185,
185,
185,
185,
185,
185,
185,
185,
185,
186,
186,
186,
187,
187,
187,
187,
187,
187,
187,
187,
187,
188,
188,
188,
188,
188,
188,
189,
189,
189,
189,
189,
189,
189,
190,
190,
190,
190,
190,
190,
191,
191,
191,
191,
191,
191,
191,
191,
192,
192,
192,
192,
193,
193,
193,
194,
194,
194,
194,
195,
195,
195,
195,
195,
195
],
"ayahBoundaries": [
0,
2,
6,
10,
20,
22,
25,
27,
31,
34,
38,
46,
48,
51,
55,
58,
59,
63,
65,
69,
73,
77,
79,
84,
88,
90,
94,
98,
103,
107,
117,
124,
129,
132,
137,
140,
145,
150,
156,
160,
167,
173,
181,
188
]
}