{"page":3,"lines":[{"line":1,"type":"text","text":"إِنَّ ٱلَّذِينَ كَفَرُوا۟ سَوَآءٌ عَلَيْهِمْ ءَأَنذَرْتَهُمْ أَمْ لَمْ تُنذِرْهُمْ","verseRange":"2:6-2:6","words":[{"location":"2:6:1","word":"إِنَّ","qpcV2":"ﱁ","tj":"إِ<rule class=ghunnah>نّ</rule>َ"},{"location":"2:6:2","word":"ٱلَّذِينَ","qpcV2":"ﱂ","tj":"<rule class=ham_wasl>ٱ</rule>لَّذِينَ"},{"location":"2:6:3","word":"كَفَرُوا۟","qpcV2":"ﱃ","tj":"كَفَرُو<rule class=slnt>اۡ</rule>"},{"location":"2:6:4","word":"سَوَآءٌ","qpcV2":"ﱄ","tj":"سَو<rule class=madda_obligatory_mottasel>َا</rule>ٓءٌ"},{"location":"2:6:5","word":"عَلَيْهِمْ","qpcV2":"ﱅ","tj":"عَلَيۡهِمۡ"},{"location":"2:6:6","word":"ءَأَنذَرْتَهُمْ","qpcV2":"ﱆ","tj":"ءَأَ<rule class=ikhafa>نذ</rule>َرۡتَهُمۡ"},{"location":"2:6:7","word":"أَمْ","qpcV2":"ﱇ","tj":"أَمۡ"},{"location":"2:6:8","word":"لَمْ","qpcV2":"ﱈ","tj":"لَمۡ"},{"location":"2:6:9","word":"تُنذِرْهُمْ","qpcV2":"ﱉ","tj":"تُ<rule class=ikhafa>نذ</rule>ِرۡهُمۡ"}]},{"line":2,"type":"text","text":"لَا يُؤْمِنُونَ ٦ خَتَمَ ٱللَّهُ عَلَىٰ قُلُوبِهِمْ وَعَلَىٰ سَمْعِهِمْ ۖ وَعَلَىٰٓ","verseRange":"2:6-2:7","words":[{"location":"2:6:10","word":"لَا","qpcV2":"ﱊ","tj":"لَا"},{"location":"2:6:11","word":"يُؤْمِنُونَ ٦","qpcV2":"ﱋ ﱌ","tj":"يُؤۡمِن<rule class=madda_permissible>ُو</rule>نَ"},{"location":"2:7:1","word":"خَتَمَ","qpcV2":"ﱍ","tj":"خَتَمَ"},{"location":"2:7:2","word":"ٱللَّهُ","qpcV2":"ﱎ","tj":"<rule class=ham_wasl>ٱ</rule>للَّهُ"},{"location":"2:7:3","word":"عَلَىٰ","qpcV2":"ﱏ","tj":"عَلَىٰ"},{"location":"2:7:4","word":"قُلُوبِهِمْ","qpcV2":"ﱐ","tj":"قُلُوبِهِمۡ"},{"location":"2:7:5","word":"وَعَلَىٰ","qpcV2":"ﱑ","tj":"وَعَلَىٰ"},{"location":"2:7:6","word":"سَمْعِهِمْ ۖ","qpcV2":"ﱒﱓ","tj":"سَمۡعِهِمۡ‌ۖ"},{"location":"2:7:7","word":"وَعَلَىٰٓ","qpcV2":"ﱔ","tj":"وَعَلَ<rule class=madda_obligatory_monfasel>ىٰٓ</rule>"}]},{"line":3,"type":"text","text":"أَبْصَـٰرِهِمْ غِشَـٰوَةٌۭ ۖ وَلَهُمْ عَذَابٌ عَظِيمٌۭ ٧ وَمِنَ ٱلنَّاسِ","verseRange":"2:7-2:8","words":[{"location":"2:7:8","word":"أَبْصَـٰرِهِمْ","qpcV2":"ﱕ","tj":"أَ<rule class=qalaqah>بۡ</rule>صَ<rule class=madda_normal>ـٰ</rule>رِهِمۡ"},{"location":"2:7:9","word":"غِشَـٰوَةٌۭ ۖ","qpcV2":"ﱖﱗ","tj":"غِشَ<rule class=madda_normal>ـٰ</rule>وَ<rule class=idgham_ghunnah>ةٌ‌ۖ</rule>"},{"location":"2:7:10","word":"وَلَهُمْ","qpcV2":"ﱘ","tj":"<rule class=idgham_ghunnah>و</rule>َلَهُمۡ"},{"location":"2:7:11","word":"عَذَابٌ","qpcV2":"ﱙ","tj":"عَذَابٌ"},{"location":"2:7:12","word":"عَظِيمٌۭ ٧","qpcV2":"ﱚ ﱛ","tj":"عَظ<rule class=madda_permissible>ِي</rule>مٌ"},{"location":"2:8:1","word":"وَمِنَ","qpcV2":"ﱜ","tj":"وَمِنَ"},{"location":"2:8:2","word":"ٱلنَّاسِ","qpcV2":"ﱝ","tj":"<rule class=ham_wasl>ٱ</rule><rule class=laam_shamsiyah>ل</rule><rule class=ghunnah>نّ</rule>َاسِ"}]},{"line":4,"type":"text","text":"مَن يَقُولُ ءَامَنَّا بِٱللَّهِ وَبِٱلْيَوْمِ ٱلْـَٔاخِرِ وَمَا هُم بِمُؤْمِنِينَ ٨","verseRange":"2:8-2:8","words":[{"location":"2:8:3","word":"مَن","qpcV2":"ﱞ","tj":"م<rule class=idgham_ghunnah>َن</rule>"},{"location":"2:8:4","word":"يَقُولُ","qpcV2":"ﱟ","tj":"<rule class=idgham_ghunnah>ي</rule>َقُولُ"},{"location":"2:8:5","word":"ءَامَنَّا","qpcV2":"ﱠ","tj":"ءَامَ<rule class=ghunnah>نّ</rule>َا"},{"location":"2:8:6","word":"بِٱللَّهِ","qpcV2":"ﱡ","tj":"بِ<rule class=ham_wasl>ٱ</rule>للَّهِ"},{"location":"2:8:7","word":"وَبِٱلْيَوْمِ","qpcV2":"ﱢ","tj":"وَبِ<rule class=ham_wasl>ٱ</rule>لۡيَوۡمِ"},{"location":"2:8:8","word":"ٱلْـَٔاخِرِ","qpcV2":"ﱣ","tj":"<rule class=ham_wasl>ٱ</rule>لۡأَخِرِ"},{"location":"2:8:9","word":"وَمَا","qpcV2":"ﱤ","tj":"وَمَا"},{"location":"2:8:10","word":"هُم","qpcV2":"ﱥ","tj":"ه<rule class=ikhafa_shafawi>ُم</rule>"},{"location":"2:8:11","word":"بِمُؤْمِنِينَ ٨","qpcV2":"ﱦ ﱧ","tj":"<rule class=ikhafa_shafawi>ب</rule>ِمُؤۡمِن<rule class=madda_permissible>ِي</rule>نَ"}]},{"line":5,"type":"text","text":"يُخَـٰدِعُونَ ٱللَّهَ وَٱلَّذِينَ ءَامَنُوا۟ وَمَا يَخْدَعُونَ إِلَّآ أَنفُسَهُمْ","verseRange":"2:9-2:9","words":[{"location":"2:9:1","word":"يُخَـٰدِعُونَ","qpcV2":"ﱨ","tj":"يُخَ<rule class=madda_normal>ـٰ</rule>دِعُونَ"},{"location":"2:9:2","word":"ٱللَّهَ","qpcV2":"ﱩ","tj":"<rule class=ham_wasl>ٱ</rule>للَّهَ"},{"location":"2:9:3","word":"وَٱلَّذِينَ","qpcV2":"ﱪ","tj":"وَ<rule class=ham_wasl>ٱ</rule>لَّذِينَ"},{"location":"2:9:4","word":"ءَامَنُوا۟","qpcV2":"ﱫ","tj":"ءَامَنُو<rule class=slnt>اۡ</rule>"},{"location":"2:9:5","word":"وَمَا","qpcV2":"ﱬ","tj":"وَمَا"},{"location":"2:9:6","word":"يَخْدَعُونَ","qpcV2":"ﱭ","tj":"يَخۡدَعُونَ"},{"location":"2:9:7","word":"إِلَّآ","qpcV2":"ﱮ","tj":"إِلّ<rule class=madda_obligatory_monfasel>َآ</rule>"},{"location":"2:9:8","word":"أَنفُسَهُمْ","qpcV2":"ﱯ","tj":"أَ<rule class=ikhafa>نف</rule>ُسَهُمۡ"}]},{"line":6,"type":"text","text":"وَمَا يَشْعُرُونَ ٩ فِى قُلُوبِهِم مَّرَضٌۭ فَزَادَهُمُ ٱللَّهُ مَرَضًۭا ۖ","verseRange":"2:9-2:10","words":[{"location":"2:9:9","word":"وَمَا","qpcV2":"ﱰ","tj":"وَمَا"},{"location":"2:9:10","word":"يَشْعُرُونَ ٩","qpcV2":"ﱱ ﱲ","tj":"يَشۡعُر<rule class=madda_permissible>ُو</rule>نَ"},{"location":"2:10:1","word":"فِى","qpcV2":"ﱳ","tj":"فِى"},{"location":"2:10:2","word":"قُلُوبِهِم","qpcV2":"ﱴ","tj":"قُلُوبِه<rule class=idgham_shafawi>ِم</rule>"},{"location":"2:10:3","word":"مَّرَضٌۭ","qpcV2":"ﱵ","tj":"<rule class=idgham_shafawi>م</rule>َّرَ<rule class=ikhafa>ضٌ</rule>"},{"location":"2:10:4","word":"فَزَادَهُمُ","qpcV2":"ﱶ","tj":"<rule class=ikhafa>ف</rule>َزَادَهُمُ"},{"location":"2:10:5","word":"ٱللَّهُ","qpcV2":"ﱷ","tj":"<rule class=ham_wasl>ٱ</rule>للَّهُ"},{"location":"2:10:6","word":"مَرَضًۭا ۖ","qpcV2":"ﱸﱹ","tj":"مَرَ<rule class=idgham_ghunnah>ضًا‌ۖ</rule>"}]},{"line":7,"type":"text","text":"وَلَهُمْ عَذَابٌ أَلِيمٌۢ بِمَا كَانُوا۟ يَكْذِبُونَ ١٠ وَإِذَا قِيلَ لَهُمْ","verseRange":"2:10-2:11","words":[{"location":"2:10:7","word":"وَلَهُمْ","qpcV2":"ﱺ","tj":"<rule class=idgham_ghunnah>و</rule>َلَهُمۡ"},{"location":"2:10:8","word":"عَذَابٌ","qpcV2":"ﱻ","tj":"عَذَابٌ"},{"location":"2:10:9","word":"أَلِيمٌۢ","qpcV2":"ﱼ","tj":"أَلِي<rule class=iqlab>مُۢ</rule>"},{"location":"2:10:10","word":"بِمَا","qpcV2":"ﱽ","tj":"<rule class=iqlab>ب</rule>ِمَا"},{"location":"2:10:11","word":"كَانُوا۟","qpcV2":"ﱾ","tj":"كَانُو<rule class=slnt>اۡ</rule>"},{"location":"2:10:12","word":"يَكْذِبُونَ ١٠","qpcV2":"ﱿ ﲀ","tj":"يَكۡذِب<rule class=madda_permissible>ُو</rule>نَ"},{"location":"2:11:1","word":"وَإِذَا","qpcV2":"ﲁ","tj":"وَإِذَا"},{"location":"2:11:2","word":"قِيلَ","qpcV2":"ﲂ","tj":"قِيلَ"},{"location":"2:11:3","word":"لَهُمْ","qpcV2":"ﲃ","tj":"لَهُمۡ"}]},{"line":8,"type":"text","text":"لَا تُفْسِدُوا۟ فِى ٱلْأَرْضِ قَالُوٓا۟ إِنَّمَا نَحْنُ مُصْلِحُونَ ١١","verseRange":"2:11-2:11","words":[{"location":"2:11:4","word":"لَا","qpcV2":"ﲄ","tj":"لَا"},{"location":"2:11:5","word":"تُفْسِدُوا۟","qpcV2":"ﲅ","tj":"تُفۡسِدُو<rule class=slnt>اۡ</rule>"},{"location":"2:11:6","word":"فِى","qpcV2":"ﲆ","tj":"فِى"},{"location":"2:11:7","word":"ٱلْأَرْضِ","qpcV2":"ﲇ","tj":"<rule class=ham_wasl>ٱ</rule>لۡأَرۡضِ"},{"location":"2:11:8","word":"قَالُوٓا۟","qpcV2":"ﲈ","tj":"قَال<rule class=madda_obligatory_mottasel>ُوٓ</rule><rule class=slnt>اۡ</rule>"},{"location":"2:11:9","word":"إِنَّمَا","qpcV2":"ﲉ","tj":"إِ<rule class=ghunnah>نّ</rule>َمَا"},{"location":"2:11:10","word":"نَحْنُ","qpcV2":"ﲊ","tj":"نَحۡنُ"},{"location":"2:11:11","word":"مُصْلِحُونَ ١١","qpcV2":"ﲋ ﲌ","tj":"مُصۡلِح<rule class=madda_permissible>ُو</rule>نَ"}]},{"line":9,"type":"text","text":"أَلَآ إِنَّهُمْ هُمُ ٱلْمُفْسِدُونَ وَلَـٰكِن لَّا يَشْعُرُونَ ١٢ وَإِذَا قِيلَ","verseRange":"2:12-2:13","words":[{"location":"2:12:1","word":"أَلَآ","qpcV2":"ﲍ","tj":"أَل<rule class=madda_obligatory_monfasel>َآ</rule>"},{"location":"2:12:2","word":"إِنَّهُمْ","qpcV2":"ﲎ","tj":"إِ<rule class=ghunnah>نّ</rule>َهُمۡ"},{"location":"2:12:3","word":"هُمُ","qpcV2":"ﲏ","tj":"هُمُ"},{"location":"2:12:4","word":"ٱلْمُفْسِدُونَ","qpcV2":"ﲐ","tj":"<rule class=ham_wasl>ٱ</rule>لۡمُفۡسِدُونَ"},{"location":"2:12:5","word":"وَلَـٰكِن","qpcV2":"ﲑ","tj":"وَلَ<rule class=madda_normal>ـٰ</rule>ك<rule class=idgham_wo_ghunnah>ِن</rule>"},{"location":"2:12:6","word":"لَّا","qpcV2":"ﲒ","tj":"<rule class=idgham_wo_ghunnah>ل</rule>َّا"},{"location":"2:12:7","word":"يَشْعُرُونَ ١٢","qpcV2":"ﲓ ﲔ","tj":"يَشۡعُر<rule class=madda_permissible>ُو</rule>نَ"},{"location":"2:13:1","word":"وَإِذَا","qpcV2":"ﲕ","tj":"وَإِذَا"},{"location":"2:13:2","word":"قِيلَ","qpcV2":"ﲖ","tj":"قِيلَ"}]},{"line":10,"type":"text","text":"لَهُمْ ءَامِنُوا۟ كَمَآ ءَامَنَ ٱلنَّاسُ قَالُوٓا۟ أَنُؤْمِنُ كَمَآ ءَامَنَ ٱلسُّفَهَآءُ ۗ","verseRange":"2:13-2:13","words":[{"location":"2:13:3","word":"لَهُمْ","qpcV2":"ﲗ","tj":"لَهُمۡ"},{"location":"2:13:4","word":"ءَامِنُوا۟","qpcV2":"ﲘ","tj":"ءَامِنُو<rule class=slnt>اۡ</rule>"},{"location":"2:13:5","word":"كَمَآ","qpcV2":"ﲙ","tj":"كَم<rule class=madda_obligatory_monfasel>َآ</rule>"},{"location":"2:13:6","word":"ءَامَنَ","qpcV2":"ﲚ","tj":"ءَامَنَ"},{"location":"2:13:7","word":"ٱلنَّاسُ","qpcV2":"ﲛ","tj":"<rule class=ham_wasl>ٱ</rule><rule class=laam_shamsiyah>ل</rule><rule class=ghunnah>نّ</rule>َاسُ"},{"location":"2:13:8","word":"قَالُوٓا۟","qpcV2":"ﲜ","tj":"قَال<rule class=madda_obligatory_mottasel>ُوٓ</rule><rule class=slnt>اۡ</rule>"},{"location":"2:13:9","word":"أَنُؤْمِنُ","qpcV2":"ﲝ","tj":"أَنُؤۡمِنُ"},{"location":"2:13:10","word":"كَمَآ","qpcV2":"ﲞ","tj":"كَم<rule class=madda_obligatory_monfasel>َآ</rule>"},{"location":"2:13:11","word":"ءَامَنَ","qpcV2":"ﲟ","tj":"ءَامَنَ"},{"location":"2:13:12","word":"ٱلسُّفَهَآءُ ۗ","qpcV2":"ﲠﲡ","tj":"<rule class=ham_wasl>ٱ</rule><rule class=laam_shamsiyah>ل</rule>سُّفَه<rule class=madda_obligatory_mottasel>َا</rule>ٓءُ‌ۗ"}]},{"line":11,"type":"text","text":"أَلَآ إِنَّهُمْ هُمُ ٱلسُّفَهَآءُ وَلَـٰكِن لَّا يَعْلَمُونَ ١٣ وَإِذَا لَقُوا۟","verseRange":"2:13-2:14","words":[{"location":"2:13:13","word":"أَلَآ","qpcV2":"ﲢ","tj":"أَل<rule class=madda_obligatory_monfasel>َآ</rule>"},{"location":"2:13:14","word":"إِنَّهُمْ","qpcV2":"ﲣ","tj":"إِ<rule class=ghunnah>نّ</rule>َهُمۡ"},{"location":"2:13:15","word":"هُمُ","qpcV2":"ﲤ","tj":"هُمُ"},{"location":"2:13:16","word":"ٱلسُّفَهَآءُ","qpcV2":"ﲥ","tj":"<rule class=ham_wasl>ٱ</rule><rule class=laam_shamsiyah>ل</rule>سُّفَه<rule class=madda_obligatory_mottasel>َا</rule>ٓءُ"},{"location":"2:13:17","word":"وَلَـٰكِن","qpcV2":"ﲦ","tj":"وَلَ<rule class=madda_normal>ـٰ</rule>ك<rule class=idgham_wo_ghunnah>ِن</rule>"},{"location":"2:13:18","word":"لَّا","qpcV2":"ﲧ","tj":"<rule class=idgham_wo_ghunnah>ل</rule>َّا"},{"location":"2:13:19","word":"يَعْلَمُونَ ١٣","qpcV2":"ﲨ ﲩ","tj":"يَعۡلَم<rule class=madda_permissible>ُو</rule>نَ"},{"location":"2:14:1","word":"وَإِذَا","qpcV2":"ﲪ","tj":"وَإِذَا"},{"location":"2:14:2","word":"لَقُوا۟","qpcV2":"ﲫ","tj":"لَقُو<rule class=slnt>اۡ</rule>"}]},{"line":12,"type":"text","text":"ٱلَّذِينَ ءَامَنُوا۟ قَالُوٓا۟ ءَامَنَّا وَإِذَا خَلَوْا۟ إِلَىٰ شَيَـٰطِينِهِمْ قَالُوٓا۟ إِنَّا","verseRange":"2:14-2:14","words":[{"location":"2:14:3","word":"ٱلَّذِينَ","qpcV2":"ﲬ","tj":"<rule class=ham_wasl>ٱ</rule>لَّذِينَ"},{"location":"2:14:4","word":"ءَامَنُوا۟","qpcV2":"ﲭ","tj":"ءَامَنُو<rule class=slnt>اۡ</rule>"},{"location":"2:14:5","word":"قَالُوٓا۟","qpcV2":"ﲮ","tj":"قَال<rule class=madda_obligatory_mottasel>ُوٓ</rule><rule class=slnt>اۡ</rule>"},{"location":"2:14:6","word":"ءَامَنَّا","qpcV2":"ﲯ","tj":"ءَامَ<rule class=ghunnah>نّ</rule>َا"},{"location":"2:14:7","word":"وَإِذَا","qpcV2":"ﲰ","tj":"وَإِذَا"},{"location":"2:14:8","word":"خَلَوْا۟","qpcV2":"ﲱ","tj":"خَلَوۡ<rule class=slnt>اۡ</rule>"},{"location":"2:14:9","word":"إِلَىٰ","qpcV2":"ﲲ","tj":"إِلَىٰ"},{"location":"2:14:10","word":"شَيَـٰطِينِهِمْ","qpcV2":"ﲳ","tj":"شَيَ<rule class=madda_normal>ـٰ</rule>طِينِهِمۡ"},{"location":"2:14:11","word":"قَالُوٓا۟","qpcV2":"ﲴ","tj":"قَال<rule class=madda_obligatory_mottasel>ُوٓ</rule><rule class=slnt>اۡ</rule>"},{"location":"2:14:12","word":"إِنَّا","qpcV2":"ﲵ","tj":"إِ<rule class=ghunnah>نّ</rule>َا"}]},{"line":13,"type":"text","text":"مَعَكُمْ إِنَّمَا نَحْنُ مُسْتَهْزِءُونَ ١٤ ٱللَّهُ يَسْتَهْزِئُ بِهِمْ وَيَمُدُّهُمْ","verseRange":"2:14-2:15","words":[{"location":"2:14:13","word":"مَعَكُمْ","qpcV2":"ﲶ","tj":"مَعَكُمۡ"},{"location":"2:14:14","word":"إِنَّمَا","qpcV2":"ﲷ","tj":"إِ<rule class=ghunnah>نّ</rule>َمَا"},{"location":"2:14:15","word":"نَحْنُ","qpcV2":"ﲸ","tj":"نَحۡنُ"},{"location":"2:14:16","word":"مُسْتَهْزِءُونَ ١٤","qpcV2":"ﲹ ﲺ","tj":"مُسۡتَهۡزِء<rule class=madda_permissible>ُو</rule>نَ"},{"location":"2:15:1","word":"ٱللَّهُ","qpcV2":"ﲻ","tj":"ٱللَّهُ"},{"location":"2:15:2","word":"يَسْتَهْزِئُ","qpcV2":"ﲼ","tj":"يَسۡتَهۡزِئُ"},{"location":"2:15:3","word":"بِهِمْ","qpcV2":"ﲽ","tj":"بِهِمۡ"},{"location":"2:15:4","word":"وَيَمُدُّهُمْ","qpcV2":"ﲾ","tj":"وَيَمُدُّهُمۡ"}]},{"line":14,"type":"text","text":"فِى طُغْيَـٰنِهِمْ يَعْمَهُونَ ١٥ أُو۟لَـٰٓئِكَ ٱلَّذِينَ ٱشْتَرَوُا۟ ٱلضَّلَـٰلَةَ","verseRange":"2:15-2:16","words":[{"location":"2:15:5","word":"فِى","qpcV2":"ﲿ","tj":"فِى"},{"location":"2:15:6","word":"طُغْيَـٰنِهِمْ","qpcV2":"ﳀ","tj":"طُغۡيَ<rule class=madda_normal>ـٰ</rule>نِهِمۡ"},{"location":"2:15:7","word":"يَعْمَهُونَ ١٥","qpcV2":"ﳁ ﳂ","tj":"يَعۡمَه<rule class=madda_permissible>ُو</rule>نَ"},{"location":"2:16:1","word":"أُو۟لَـٰٓئِكَ","qpcV2":"ﳃ","tj":"أُ<rule class=slnt>وۡ</rule>لَ<rule class=madda_obligatory_mottasel>ـٰٓ</rule>ئِكَ"},{"location":"2:16:2","word":"ٱلَّذِينَ","qpcV2":"ﳄ","tj":"<rule class=ham_wasl>ٱ</rule>لَّذِينَ"},{"location":"2:16:3","word":"ٱشْتَرَوُا۟","qpcV2":"ﳅ","tj":"<rule class=ham_wasl>ٱ</rule>شۡتَرَوُ<rule class=slnt>اۡ</rule>"},{"location":"2:16:4","word":"ٱلضَّلَـٰلَةَ","qpcV2":"ﳆ","tj":"<rule class=ham_wasl>ٱ</rule><rule class=laam_shamsiyah>ل</rule>ضَّلَ<rule class=madda_normal>ـٰ</rule>لَةَ"}]},{"line":15,"type":"text","text":"بِٱلْهُدَىٰ فَمَا رَبِحَت تِّجَـٰرَتُهُمْ وَمَا كَانُوا۟ مُهْتَدِينَ ١٦","verseRange":"2:16-2:16","words":[{"location":"2:16:5","word":"بِٱلْهُدَىٰ","qpcV2":"ﳇ","tj":"بِ<rule class=ham_wasl>ٱ</rule>لۡهُدَىٰ"},{"location":"2:16:6","word":"فَمَا","qpcV2":"ﳈ","tj":"فَمَا"},{"location":"2:16:7","word":"رَبِحَت","qpcV2":"ﳉ","tj":"رَبِحَت"},{"location":"2:16:8","word":"تِّجَـٰرَتُهُمْ","qpcV2":"ﳊ","tj":"تِّجَ<rule class=madda_normal>ـٰ</rule>رَتُهُمۡ"},{"location":"2:16:9","word":"وَمَا","qpcV2":"ﳋ","tj":"وَمَا"},{"location":"2:16:10","word":"كَانُوا۟","qpcV2":"ﳌ","tj":"كَانُو<rule class=slnt>اۡ</rule>"},{"location":"2:16:11","word":"مُهْتَدِينَ ١٦","qpcV2":"ﳍ ﳎ","tj":"مُهۡتَد<rule class=madda_permissible>ِي</rule>نَ"}]}]}