{"page":356,"lines":[{"line":1,"type":"text","text":"يُقَلِّبُ ٱللَّهُ ٱلَّيْلَ وَٱلنَّهَارَ ۚ إِنَّ فِى ذَٰلِكَ لَعِبْرَةًۭ لِّأُو۟لِى ٱلْأَبْصَـٰرِ ٤٤","verseRange":"24:44-24:44","words":[{"location":"24:44:1","word":"يُقَلِّبُ","qpcV2":"ﱁ","tj":"يُقَلِّبُ"},{"location":"24:44:2","word":"ٱللَّهُ","qpcV2":"ﱂ","tj":"<rule class=ham_wasl>ٱ</rule>للَّهُ"},{"location":"24:44:3","word":"ٱلَّيْلَ","qpcV2":"ﱃ","tj":"<rule class=ham_wasl>ٱ</rule>لَّيۡلَ"},{"location":"24:44:4","word":"وَٱلنَّهَارَ ۚ","qpcV2":"ﱄﱅ","tj":"وَ<rule class=ham_wasl>ٱ</rule><rule class=laam_shamsiyah>ل</rule><rule class=ghunnah>نّ</rule>َهَارَ‌ۚ"},{"location":"24:44:5","word":"إِنَّ","qpcV2":"ﱆ","tj":"إِ<rule class=ghunnah>نّ</rule>َ"},{"location":"24:44:6","word":"فِى","qpcV2":"ﱇ","tj":"فِى"},{"location":"24:44:7","word":"ذَٰلِكَ","qpcV2":"ﱈ","tj":"ذ<rule class=madda_normal><rule class=custom-alef-maksora>ٰ</rule></rule>لِكَ"},{"location":"24:44:8","word":"لَعِبْرَةًۭ","qpcV2":"ﱉ","tj":"لَعِ<rule class=qalaqah>بۡ</rule>رَ<rule class=idgham_wo_ghunnah>ةً</rule>"},{"location":"24:44:9","word":"لِّأُو۟لِى","qpcV2":"ﱊ","tj":"<rule class=idgham_wo_ghunnah>ل</rule>ِّأُ<rule class=slnt>وۡ</rule>لِى"},{"location":"24:44:10","word":"ٱلْأَبْصَـٰرِ ٤٤","qpcV2":"ﱋ ﱌ","tj":"<rule class=ham_wasl>ٱ</rule>لۡأَ<rule class=qalaqah>بۡ</rule>صَ<rule class=madda_permissible>ـٰ</rule>رِ"}]},{"line":2,"type":"text","text":"وَٱللَّهُ خَلَقَ كُلَّ دَآبَّةٍۢ مِّن مَّآءٍۢ ۖ فَمِنْهُم مَّن يَمْشِى عَلَىٰ بَطْنِهِۦ وَمِنْهُم مَّن","verseRange":"24:45-24:45","words":[{"location":"24:45:1","word":"وَٱللَّهُ","qpcV2":"ﱍ","tj":"وَ<rule class=ham_wasl>ٱ</rule>للَّهُ"},{"location":"24:45:2","word":"خَلَقَ","qpcV2":"ﱎ","tj":"خَلَقَ"},{"location":"24:45:3","word":"كُلَّ","qpcV2":"ﱏ","tj":"كُلَّ"},{"location":"24:45:4","word":"دَآبَّةٍۢ","qpcV2":"ﱐ","tj":"د<rule class=madda_necessary>َا</rule>ٓبَّ<rule class=idgham_ghunnah>ةٍ</rule>"},{"location":"24:45:5","word":"مِّن","qpcV2":"ﱑ","tj":"<rule class=idgham_ghunnah>م</rule>ّ<rule class=idgham_ghunnah>ِن</rule>"},{"location":"24:45:6","word":"مَّآءٍۢ ۖ","qpcV2":"ﱒﱓ","tj":"<rule class=idgham_ghunnah>م</rule>ّ<rule class=madda_obligatory_mottasel>َا</rule>ٓ<rule class=ikhafa>ءٍ‌ۖ</rule>"},{"location":"24:45:7","word":"فَمِنْهُم","qpcV2":"ﱔ","tj":"<rule class=ikhafa>ف</rule>َمِنۡه<rule class=idgham_shafawi>ُم</rule>"},{"location":"24:45:8","word":"مَّن","qpcV2":"ﱕ","tj":"<rule class=idgham_shafawi>م</rule>ّ<rule class=idgham_ghunnah>َن</rule>"},{"location":"24:45:9","word":"يَمْشِى","qpcV2":"ﱖ","tj":"<rule class=idgham_ghunnah>ي</rule>َمۡشِى"},{"location":"24:45:10","word":"عَلَىٰ","qpcV2":"ﱗ","tj":"عَلَىٰ"},{"location":"24:45:11","word":"بَطْنِهِۦ","qpcV2":"ﱘ","tj":"بَ<rule class=qalaqah>طۡ</rule>نِه<rule class=madda_normal>ِۦ</rule>"},{"location":"24:45:12","word":"وَمِنْهُم","qpcV2":"ﱙ","tj":"وَمِنۡه<rule class=idgham_shafawi>ُم</rule>"},{"location":"24:45:13","word":"مَّن","qpcV2":"ﱚ","tj":"<rule class=idgham_shafawi>م</rule>ّ<rule class=idgham_ghunnah>َن</rule>"}]},{"line":3,"type":"text","text":"يَمْشِى عَلَىٰ رِجْلَيْنِ وَمِنْهُم مَّن يَمْشِى عَلَىٰٓ أَرْبَعٍۢ ۚ يَخْلُقُ ٱللَّهُ مَا يَشَآءُ ۚ","verseRange":"24:45-24:45","words":[{"location":"24:45:14","word":"يَمْشِى","qpcV2":"ﱛ","tj":"<rule class=idgham_ghunnah>ي</rule>َمۡشِى"},{"location":"24:45:15","word":"عَلَىٰ","qpcV2":"ﱜ","tj":"عَلَىٰ"},{"location":"24:45:16","word":"رِجْلَيْنِ","qpcV2":"ﱝ","tj":"رِ<rule class=qalaqah>جۡ</rule>لَيۡنِ"},{"location":"24:45:17","word":"وَمِنْهُم","qpcV2":"ﱞ","tj":"وَمِنۡه<rule class=idgham_shafawi>ُم</rule>"},{"location":"24:45:18","word":"مَّن","qpcV2":"ﱟ","tj":"<rule class=idgham_shafawi>م</rule>ّ<rule class=idgham_ghunnah>َن</rule>"},{"location":"24:45:19","word":"يَمْشِى","qpcV2":"ﱠ","tj":"<rule class=idgham_ghunnah>ي</rule>َمۡشِى"},{"location":"24:45:20","word":"عَلَىٰٓ","qpcV2":"ﱡ","tj":"عَلَ<rule class=madda_obligatory_monfasel>ىٰٓ</rule>"},{"location":"24:45:21","word":"أَرْبَعٍۢ ۚ","qpcV2":"ﱢﱣ","tj":"أَرۡبَ<rule class=idgham_ghunnah>عٍ‌ۚ</rule>"},{"location":"24:45:22","word":"يَخْلُقُ","qpcV2":"ﱤ","tj":"<rule class=idgham_ghunnah>ي</rule>َخۡلُقُ"},{"location":"24:45:23","word":"ٱللَّهُ","qpcV2":"ﱥ","tj":"<rule class=ham_wasl>ٱ</rule>للَّهُ"},{"location":"24:45:24","word":"مَا","qpcV2":"ﱦ","tj":"مَا"},{"location":"24:45:25","word":"يَشَآءُ ۚ","qpcV2":"ﱧﱨ","tj":"يَش<rule class=madda_obligatory_mottasel>َا</rule>ٓءُ‌ۚ"}]},{"line":4,"type":"text","text":"إِنَّ ٱللَّهَ عَلَىٰ كُلِّ شَىْءٍۢ قَدِيرٌۭ ٤٥ لَّقَدْ أَنزَلْنَآ ءَايَـٰتٍۢ مُّبَيِّنَـٰتٍۢ ۚ","verseRange":"24:45-24:46","words":[{"location":"24:45:26","word":"إِنَّ","qpcV2":"ﱩ","tj":"إِ<rule class=ghunnah>نّ</rule>َ"},{"location":"24:45:27","word":"ٱللَّهَ","qpcV2":"ﱪ","tj":"<rule class=ham_wasl>ٱ</rule>للَّهَ"},{"location":"24:45:28","word":"عَلَىٰ","qpcV2":"ﱫ","tj":"عَلَىٰ"},{"location":"24:45:29","word":"كُلِّ","qpcV2":"ﱬ","tj":"كُلِّ"},{"location":"24:45:30","word":"شَىْءٍۢ","qpcV2":"ﱭ","tj":"ش<rule class=ikhafa>َىۡءٍ</rule>"},{"location":"24:45:31","word":"قَدِيرٌۭ ٤٥","qpcV2":"ﱮ ﱯ","tj":"<rule class=ikhafa>ق</rule>َد<rule class=madda_permissible>ِي</rule>رٌ"},{"location":"24:46:1","word":"لَّقَدْ","qpcV2":"ﱰ","tj":"لَّقَ<rule class=qalaqah>دۡ</rule>"},{"location":"24:46:2","word":"أَنزَلْنَآ","qpcV2":"ﱱ","tj":"أَ<rule class=ikhafa>نز</rule>َلۡن<rule class=madda_obligatory_monfasel>َآ</rule>"},{"location":"24:46:3","word":"ءَايَـٰتٍۢ","qpcV2":"ﱲ","tj":"ءَايَ<rule class=madda_normal>ـٰ</rule><rule class=idgham_ghunnah>تٍ</rule>"},{"location":"24:46:4","word":"مُّبَيِّنَـٰتٍۢ ۚ","qpcV2":"ﱳﱴ","tj":"<rule class=idgham_ghunnah>م</rule>ُّبَيِّنَ<rule class=madda_normal>ـٰ</rule><rule class=idgham_ghunnah>تٍ‌ۚ</rule>"}]},{"line":5,"type":"text","text":"وَٱللَّهُ يَهْدِى مَن يَشَآءُ إِلَىٰ صِرَٰطٍۢ مُّسْتَقِيمٍۢ ٤٦ وَيَقُولُونَ","verseRange":"24:46-24:47","words":[{"location":"24:46:5","word":"وَٱللَّهُ","qpcV2":"ﱵ","tj":"<rule class=idgham_ghunnah>و</rule>َ<rule class=ham_wasl>ٱ</rule>للَّهُ"},{"location":"24:46:6","word":"يَهْدِى","qpcV2":"ﱶ","tj":"يَهۡدِى"},{"location":"24:46:7","word":"مَن","qpcV2":"ﱷ","tj":"م<rule class=idgham_ghunnah>َن</rule>"},{"location":"24:46:8","word":"يَشَآءُ","qpcV2":"ﱸ","tj":"<rule class=idgham_ghunnah>ي</rule>َش<rule class=madda_obligatory_mottasel>َا</rule>ٓءُ"},{"location":"24:46:9","word":"إِلَىٰ","qpcV2":"ﱹ","tj":"إِلَىٰ"},{"location":"24:46:10","word":"صِرَٰطٍۢ","qpcV2":"ﱺ","tj":"صِر<rule class=madda_normal><rule class=custom-alef-maksora>ٰ</rule></rule><rule class=idgham_ghunnah>طٍ</rule>"},{"location":"24:46:11","word":"مُّسْتَقِيمٍۢ ٤٦","qpcV2":"ﱻ ﱼ","tj":"<rule class=idgham_ghunnah>م</rule>ُّسۡتَق<rule class=madda_permissible>ِي</rule>مٍ"},{"location":"24:47:1","word":"وَيَقُولُونَ","qpcV2":"ﱽ","tj":"وَيَقُولُونَ"}]},{"line":6,"type":"text","text":"ءَامَنَّا بِٱللَّهِ وَبِٱلرَّسُولِ وَأَطَعْنَا ثُمَّ يَتَوَلَّىٰ فَرِيقٌۭ مِّنْهُم مِّنۢ بَعْدِ","verseRange":"24:47-24:47","words":[{"location":"24:47:2","word":"ءَامَنَّا","qpcV2":"ﱾ","tj":"ءَامَ<rule class=ghunnah>نّ</rule>َا"},{"location":"24:47:3","word":"بِٱللَّهِ","qpcV2":"ﱿ","tj":"بِ<rule class=ham_wasl>ٱ</rule>للَّهِ"},{"location":"24:47:4","word":"وَبِٱلرَّسُولِ","qpcV2":"ﲀ","tj":"وَبِ<rule class=ham_wasl>ٱ</rule><rule class=laam_shamsiyah>ل</rule>رَّسُولِ"},{"location":"24:47:5","word":"وَأَطَعْنَا","qpcV2":"ﲁ","tj":"وَأَطَعۡنَا"},{"location":"24:47:6","word":"ثُمَّ","qpcV2":"ﲂ","tj":"ثُ<rule class=ghunnah>مّ</rule>َ"},{"location":"24:47:7","word":"يَتَوَلَّىٰ","qpcV2":"ﲃ","tj":"يَتَوَلَّىٰ"},{"location":"24:47:8","word":"فَرِيقٌۭ","qpcV2":"ﲄ","tj":"فَرِي<rule class=idgham_ghunnah>قٌ</rule>"},{"location":"24:47:9","word":"مِّنْهُم","qpcV2":"ﲅ","tj":"<rule class=idgham_ghunnah>م</rule>ِّنۡه<rule class=idgham_shafawi>ُم</rule>"},{"location":"24:47:10","word":"مِّنۢ","qpcV2":"ﲆ","tj":"<rule class=idgham_shafawi>م</rule>ّ<rule class=iqlab>ِنۢ</rule>"},{"location":"24:47:11","word":"بَعْدِ","qpcV2":"ﲇ","tj":"<rule class=iqlab>ب</rule>َعۡدِ"}]},{"line":7,"type":"text","text":"ذَٰلِكَ ۚ وَمَآ أُو۟لَـٰٓئِكَ بِٱلْمُؤْمِنِينَ ٤٧ وَإِذَا دُعُوٓا۟ إِلَى ٱللَّهِ وَرَسُولِهِۦ","verseRange":"24:47-24:48","words":[{"location":"24:47:12","word":"ذَٰلِكَ ۚ","qpcV2":"ﲈﲉ","tj":"ذ<rule class=madda_normal><rule class=custom-alef-maksora>ٰ</rule></rule>لِكَ‌ۚ"},{"location":"24:47:13","word":"وَمَآ","qpcV2":"ﲊ","tj":"وَم<rule class=madda_obligatory_monfasel>َآ</rule>"},{"location":"24:47:14","word":"أُو۟لَـٰٓئِكَ","qpcV2":"ﲋ","tj":"أُ<rule class=slnt>وۡ</rule>لَ<rule class=madda_obligatory_mottasel>ـٰٓ</rule>ئِكَ"},{"location":"24:47:15","word":"بِٱلْمُؤْمِنِينَ ٤٧","qpcV2":"ﲌ ﲍ","tj":"بِ<rule class=ham_wasl>ٱ</rule>لۡمُؤۡمِن<rule class=madda_permissible>ِي</rule>نَ"},{"location":"24:48:1","word":"وَإِذَا","qpcV2":"ﲎ","tj":"وَإِذَا"},{"location":"24:48:2","word":"دُعُوٓا۟","qpcV2":"ﲏ","tj":"دُع<rule class=madda_obligatory_mottasel>ُوٓ</rule><rule class=slnt>اۡ</rule>"},{"location":"24:48:3","word":"إِلَى","qpcV2":"ﲐ","tj":"إِلَى"},{"location":"24:48:4","word":"ٱللَّهِ","qpcV2":"ﲑ","tj":"<rule class=ham_wasl>ٱ</rule>للَّهِ"},{"location":"24:48:5","word":"وَرَسُولِهِۦ","qpcV2":"ﲒ","tj":"وَرَسُولِه<rule class=madda_normal>ِۦ</rule>"}]},{"line":8,"type":"text","text":"لِيَحْكُمَ بَيْنَهُمْ إِذَا فَرِيقٌۭ مِّنْهُم مُّعْرِضُونَ ٤٨ وَإِن يَكُن لَّهُمُ ٱلْحَقُّ","verseRange":"24:48-24:49","words":[{"location":"24:48:6","word":"لِيَحْكُمَ","qpcV2":"ﲓ","tj":"لِيَحۡكُمَ"},{"location":"24:48:7","word":"بَيْنَهُمْ","qpcV2":"ﲔ","tj":"بَيۡنَهُمۡ"},{"location":"24:48:8","word":"إِذَا","qpcV2":"ﲕ","tj":"إِذَا"},{"location":"24:48:9","word":"فَرِيقٌۭ","qpcV2":"ﲖ","tj":"فَرِي<rule class=idgham_ghunnah>قٌ</rule>"},{"location":"24:48:10","word":"مِّنْهُم","qpcV2":"ﲗ","tj":"<rule class=idgham_ghunnah>م</rule>ِّنۡه<rule class=idgham_shafawi>ُم</rule>"},{"location":"24:48:11","word":"مُّعْرِضُونَ ٤٨","qpcV2":"ﲘ ﲙ","tj":"<rule class=idgham_shafawi>م</rule>ُّعۡرِض<rule class=madda_permissible>ُو</rule>نَ"},{"location":"24:49:1","word":"وَإِن","qpcV2":"ﲚ","tj":"وَإ<rule class=idgham_ghunnah>ِن</rule>"},{"location":"24:49:2","word":"يَكُن","qpcV2":"ﲛ","tj":"<rule class=idgham_ghunnah>ي</rule>َك<rule class=idgham_wo_ghunnah>ُن</rule>"},{"location":"24:49:3","word":"لَّهُمُ","qpcV2":"ﲜ","tj":"<rule class=idgham_wo_ghunnah>ل</rule>َّهُمُ"},{"location":"24:49:4","word":"ٱلْحَقُّ","qpcV2":"ﲝ","tj":"<rule class=ham_wasl>ٱ</rule>لۡحَقُّ"}]},{"line":9,"type":"text","text":"يَأْتُوٓا۟ إِلَيْهِ مُذْعِنِينَ ٤٩ أَفِى قُلُوبِهِم مَّرَضٌ أَمِ ٱرْتَابُوٓا۟ أَمْ يَخَافُونَ","verseRange":"24:49-24:50","words":[{"location":"24:49:5","word":"يَأْتُوٓا۟","qpcV2":"ﲞ","tj":"يَأۡت<rule class=madda_obligatory_mottasel>ُوٓ</rule><rule class=slnt>اۡ</rule>"},{"location":"24:49:6","word":"إِلَيْهِ","qpcV2":"ﲟ","tj":"إِلَيۡهِ"},{"location":"24:49:7","word":"مُذْعِنِينَ ٤٩","qpcV2":"ﲠ ﲡ","tj":"مُذۡعِن<rule class=madda_permissible>ِي</rule>نَ"},{"location":"24:50:1","word":"أَفِى","qpcV2":"ﲢ","tj":"أَفِى"},{"location":"24:50:2","word":"قُلُوبِهِم","qpcV2":"ﲣ","tj":"قُلُوبِه<rule class=idgham_shafawi>ِم</rule>"},{"location":"24:50:3","word":"مَّرَضٌ","qpcV2":"ﲤ","tj":"<rule class=idgham_shafawi>م</rule>َّرَضٌ"},{"location":"24:50:4","word":"أَمِ","qpcV2":"ﲥ","tj":"أَمِ"},{"location":"24:50:5","word":"ٱرْتَابُوٓا۟","qpcV2":"ﲦ","tj":"<rule class=ham_wasl>ٱ</rule>رۡتَاب<rule class=madda_obligatory_mottasel>ُوٓ</rule><rule class=slnt>اۡ</rule>"},{"location":"24:50:6","word":"أَمْ","qpcV2":"ﲧ","tj":"أَمۡ"},{"location":"24:50:7","word":"يَخَافُونَ","qpcV2":"ﲨ","tj":"يَخَافُونَ"}]},{"line":10,"type":"text","text":"أَن يَحِيفَ ٱللَّهُ عَلَيْهِمْ وَرَسُولُهُۥ ۚ بَلْ أُو۟لَـٰٓئِكَ هُمُ ٱلظَّـٰلِمُونَ ٥٠","verseRange":"24:50-24:50","words":[{"location":"24:50:8","word":"أَن","qpcV2":"ﲩ","tj":"أ<rule class=idgham_ghunnah>َن</rule>"},{"location":"24:50:9","word":"يَحِيفَ","qpcV2":"ﲪ","tj":"<rule class=idgham_ghunnah>ي</rule>َحِيفَ"},{"location":"24:50:10","word":"ٱللَّهُ","qpcV2":"ﲫ","tj":"<rule class=ham_wasl>ٱ</rule>للَّهُ"},{"location":"24:50:11","word":"عَلَيْهِمْ","qpcV2":"ﲬ","tj":"عَلَيۡهِمۡ"},{"location":"24:50:12","word":"وَرَسُولُهُۥ ۚ","qpcV2":"ﲭﲮ","tj":"وَرَسُولُهُ<rule class=madda_normal>ۥ</rule>‌ۚ"},{"location":"24:50:13","word":"بَلْ","qpcV2":"ﲯ","tj":"بَلۡ"},{"location":"24:50:14","word":"أُو۟لَـٰٓئِكَ","qpcV2":"ﲰ","tj":"أُ<rule class=slnt>وۡ</rule>لَ<rule class=madda_obligatory_mottasel>ـٰٓ</rule>ئِكَ"},{"location":"24:50:15","word":"هُمُ","qpcV2":"ﲱ","tj":"هُمُ"},{"location":"24:50:16","word":"ٱلظَّـٰلِمُونَ ٥٠","qpcV2":"ﲲ ﲳ","tj":"<rule class=ham_wasl>ٱ</rule><rule class=laam_shamsiyah>ل</rule>ظَّ<rule class=madda_normal>ـٰ</rule>لِم<rule class=madda_permissible>ُو</rule>نَ"}]},{"line":11,"type":"text","text":"إِنَّمَا كَانَ قَوْلَ ٱلْمُؤْمِنِينَ إِذَا دُعُوٓا۟ إِلَى ٱللَّهِ وَرَسُولِهِۦ لِيَحْكُمَ بَيْنَهُمْ","verseRange":"24:51-24:51","words":[{"location":"24:51:1","word":"إِنَّمَا","qpcV2":"ﲴ","tj":"إِ<rule class=ghunnah>نّ</rule>َمَا"},{"location":"24:51:2","word":"كَانَ","qpcV2":"ﲵ","tj":"كَانَ"},{"location":"24:51:3","word":"قَوْلَ","qpcV2":"ﲶ","tj":"قَوۡلَ"},{"location":"24:51:4","word":"ٱلْمُؤْمِنِينَ","qpcV2":"ﲷ","tj":"<rule class=ham_wasl>ٱ</rule>لۡمُؤۡمِنِينَ"},{"location":"24:51:5","word":"إِذَا","qpcV2":"ﲸ","tj":"إِذَا"},{"location":"24:51:6","word":"دُعُوٓا۟","qpcV2":"ﲹ","tj":"دُع<rule class=madda_obligatory_mottasel>ُوٓ</rule><rule class=slnt>اۡ</rule>"},{"location":"24:51:7","word":"إِلَى","qpcV2":"ﲺ","tj":"إِلَى"},{"location":"24:51:8","word":"ٱللَّهِ","qpcV2":"ﲻ","tj":"<rule class=ham_wasl>ٱ</rule>للَّهِ"},{"location":"24:51:9","word":"وَرَسُولِهِۦ","qpcV2":"ﲼ","tj":"وَرَسُولِه<rule class=madda_normal>ِۦ</rule>"},{"location":"24:51:10","word":"لِيَحْكُمَ","qpcV2":"ﲽ","tj":"لِيَحۡكُمَ"},{"location":"24:51:11","word":"بَيْنَهُمْ","qpcV2":"ﲾ","tj":"بَيۡنَهُمۡ"}]},{"line":12,"type":"text","text":"أَن يَقُولُوا۟ سَمِعْنَا وَأَطَعْنَا ۚ وَأُو۟لَـٰٓئِكَ هُمُ ٱلْمُفْلِحُونَ ٥١ وَمَن","verseRange":"24:51-24:52","words":[{"location":"24:51:12","word":"أَن","qpcV2":"ﲿ","tj":"أ<rule class=idgham_ghunnah>َن</rule>"},{"location":"24:51:13","word":"يَقُولُوا۟","qpcV2":"ﳀ","tj":"<rule class=idgham_ghunnah>ي</rule>َقُولُو<rule class=slnt>اۡ</rule>"},{"location":"24:51:14","word":"سَمِعْنَا","qpcV2":"ﳁ","tj":"سَمِعۡنَا"},{"location":"24:51:15","word":"وَأَطَعْنَا ۚ","qpcV2":"ﳂﳃ","tj":"وَأَطَعۡنَا‌ۚ"},{"location":"24:51:16","word":"وَأُو۟لَـٰٓئِكَ","qpcV2":"ﳄ","tj":"وَأُ<rule class=slnt>وۡ</rule>لَ<rule class=madda_obligatory_mottasel>ـٰٓ</rule>ئِكَ"},{"location":"24:51:17","word":"هُمُ","qpcV2":"ﳅ","tj":"هُمُ"},{"location":"24:51:18","word":"ٱلْمُفْلِحُونَ ٥١","qpcV2":"ﳆ ﳇ","tj":"<rule class=ham_wasl>ٱ</rule>لۡمُفۡلِح<rule class=madda_permissible>ُو</rule>نَ"},{"location":"24:52:1","word":"وَمَن","qpcV2":"ﳈ","tj":"وَم<rule class=idgham_ghunnah>َن</rule>"}]},{"line":13,"type":"text","text":"يُطِعِ ٱللَّهَ وَرَسُولَهُۥ وَيَخْشَ ٱللَّهَ وَيَتَّقْهِ فَأُو۟لَـٰٓئِكَ هُمُ ٱلْفَآئِزُونَ ٥٢","verseRange":"24:52-24:52","words":[{"location":"24:52:2","word":"يُطِعِ","qpcV2":"ﳉ","tj":"<rule class=idgham_ghunnah>ي</rule>ُطِعِ"},{"location":"24:52:3","word":"ٱللَّهَ","qpcV2":"ﳊ","tj":"<rule class=ham_wasl>ٱ</rule>للَّهَ"},{"location":"24:52:4","word":"وَرَسُولَهُۥ","qpcV2":"ﳋ","tj":"وَرَسُولَهُ<rule class=madda_normal>ۥ</rule>"},{"location":"24:52:5","word":"وَيَخْشَ","qpcV2":"ﳌ","tj":"وَيَخۡشَ"},{"location":"24:52:6","word":"ٱللَّهَ","qpcV2":"ﳍ","tj":"<rule class=ham_wasl>ٱ</rule>للَّهَ"},{"location":"24:52:7","word":"وَيَتَّقْهِ","qpcV2":"ﳎ","tj":"وَيَتَّ<rule class=qalaqah>قۡ</rule>هِ"},{"location":"24:52:8","word":"فَأُو۟لَـٰٓئِكَ","qpcV2":"ﳏ","tj":"فَأُ<rule class=slnt>وۡ</rule>لَ<rule class=madda_obligatory_mottasel>ـٰٓ</rule>ئِكَ"},{"location":"24:52:9","word":"هُمُ","qpcV2":"ﳐ","tj":"هُمُ"},{"location":"24:52:10","word":"ٱلْفَآئِزُونَ ٥٢","qpcV2":"ﳑ ﳒ","tj":"<rule class=ham_wasl>ٱ</rule>لۡف<rule class=madda_obligatory_mottasel>َا</rule>ٓئِز<rule class=madda_permissible>ُو</rule>نَ"}]},{"line":14,"type":"text","text":"۞ وَأَقْسَمُوا۟ بِٱللَّهِ جَهْدَ أَيْمَـٰنِهِمْ لَئِنْ أَمَرْتَهُمْ لَيَخْرُجُنَّ ۖ قُل","verseRange":"24:53-24:53","words":[{"location":"24:53:1","word":"۞ وَأَقْسَمُوا۟","qpcV2":"ﳓﳔ","tj":"۞وَأَ<rule class=qalaqah>قۡ</rule>سَمُو<rule class=slnt>اۡ</rule>"},{"location":"24:53:2","word":"بِٱللَّهِ","qpcV2":"ﳕ","tj":"بِ<rule class=ham_wasl>ٱ</rule>للَّهِ"},{"location":"24:53:3","word":"جَهْدَ","qpcV2":"ﳖ","tj":"جَهۡدَ"},{"location":"24:53:4","word":"أَيْمَـٰنِهِمْ","qpcV2":"ﳗ","tj":"أَيۡمَ<rule class=madda_normal>ـٰ</rule>نِهِمۡ"},{"location":"24:53:5","word":"لَئِنْ","qpcV2":"ﳘ","tj":"لَئِنۡ"},{"location":"24:53:6","word":"أَمَرْتَهُمْ","qpcV2":"ﳙ","tj":"أَمَرۡتَهُمۡ"},{"location":"24:53:7","word":"لَيَخْرُجُنَّ ۖ","qpcV2":"ﳚﳛ","tj":"لَيَخۡرُجُ<rule class=ghunnah>نّ</rule>َ‌ۖ"},{"location":"24:53:8","word":"قُل","qpcV2":"ﳜ","tj":"قُل"}]},{"line":15,"type":"text","text":"لَّا تُقْسِمُوا۟ ۖ طَاعَةٌۭ مَّعْرُوفَةٌ ۚ إِنَّ ٱللَّهَ خَبِيرٌۢ بِمَا تَعْمَلُونَ ٥٣","verseRange":"24:53-24:53","words":[{"location":"24:53:9","word":"لَّا","qpcV2":"ﳝ","tj":"لَّا"},{"location":"24:53:10","word":"تُقْسِمُوا۟ ۖ","qpcV2":"ﳞﳟ","tj":"تُ<rule class=qalaqah>قۡ</rule>سِمُو<rule class=slnt>اۡ‌ۖ</rule>"},{"location":"24:53:11","word":"طَاعَةٌۭ","qpcV2":"ﳠ","tj":"طَاعَ<rule class=idgham_ghunnah>ةٌ</rule>"},{"location":"24:53:12","word":"مَّعْرُوفَةٌ ۚ","qpcV2":"ﳡﳢ","tj":"<rule class=idgham_ghunnah>م</rule>َّعۡرُوفَةٌ‌ۚ"},{"location":"24:53:13","word":"إِنَّ","qpcV2":"ﳣ","tj":"إِ<rule class=ghunnah>نّ</rule>َ"},{"location":"24:53:14","word":"ٱللَّهَ","qpcV2":"ﳤ","tj":"<rule class=ham_wasl>ٱ</rule>للَّهَ"},{"location":"24:53:15","word":"خَبِيرٌۢ","qpcV2":"ﳥ","tj":"خَبِي<rule class=iqlab>رُۢ</rule>"},{"location":"24:53:16","word":"بِمَا","qpcV2":"ﳦ","tj":"<rule class=iqlab>ب</rule>ِمَا"},{"location":"24:53:17","word":"تَعْمَلُونَ ٥٣","qpcV2":"ﳧ ﳨ","tj":"تَعۡمَل<rule class=madda_permissible>ُو</rule>نَ"}]}]}