{"page":17,"lines":[{"line":1,"type":"text","text":"۞ مَا نَنسَخْ مِنْ ءَايَةٍ أَوْ نُنسِهَا نَأْتِ بِخَيْرٍۢ مِّنْهَآ أَوْ مِثْلِهَآ ۗ","verseRange":"2:106-2:106","words":[{"location":"2:106:1","word":"۞ مَا","qpcV2":"ﱁﱂ","tj":"۞مَا"},{"location":"2:106:2","word":"نَنسَخْ","qpcV2":"ﱃ","tj":"نَ<rule class=ikhafa>نس</rule>َخۡ"},{"location":"2:106:3","word":"مِنْ","qpcV2":"ﱄ","tj":"مِنۡ"},{"location":"2:106:4","word":"ءَايَةٍ","qpcV2":"ﱅ","tj":"ءَايَةٍ"},{"location":"2:106:5","word":"أَوْ","qpcV2":"ﱆ","tj":"أَوۡ"},{"location":"2:106:6","word":"نُنسِهَا","qpcV2":"ﱇ","tj":"نُ<rule class=ikhafa>نس</rule>ِهَا"},{"location":"2:106:7","word":"نَأْتِ","qpcV2":"ﱈ","tj":"نَأۡتِ"},{"location":"2:106:8","word":"بِخَيْرٍۢ","qpcV2":"ﱉ","tj":"بِخَيۡ<rule class=idgham_ghunnah>رٍ</rule>"},{"location":"2:106:9","word":"مِّنْهَآ","qpcV2":"ﱊ","tj":"<rule class=idgham_ghunnah>م</rule>ِّنۡه<rule class=madda_obligatory_monfasel>َآ</rule>"},{"location":"2:106:10","word":"أَوْ","qpcV2":"ﱋ","tj":"أَوۡ"},{"location":"2:106:11","word":"مِثْلِهَآ ۗ","qpcV2":"ﱌﱍ","tj":"مِثۡلِه<rule class=madda_obligatory_monfasel>َآ‌ۗ</rule>"}]},{"line":2,"type":"text","text":"أَلَمْ تَعْلَمْ أَنَّ ٱللَّهَ عَلَىٰ كُلِّ شَىْءٍۢ قَدِيرٌ ١٠٦ أَلَمْ تَعْلَمْ أَنَّ ٱللَّهَ لَهُۥ","verseRange":"2:106-2:107","words":[{"location":"2:106:12","word":"أَلَمْ","qpcV2":"ﱎ","tj":"أَلَمۡ"},{"location":"2:106:13","word":"تَعْلَمْ","qpcV2":"ﱏ","tj":"تَعۡلَمۡ"},{"location":"2:106:14","word":"أَنَّ","qpcV2":"ﱐ","tj":"أَ<rule class=ghunnah>نّ</rule>َ"},{"location":"2:106:15","word":"ٱللَّهَ","qpcV2":"ﱑ","tj":"<rule class=ham_wasl>ٱ</rule>للَّهَ"},{"location":"2:106:16","word":"عَلَىٰ","qpcV2":"ﱒ","tj":"عَلَىٰ"},{"location":"2:106:17","word":"كُلِّ","qpcV2":"ﱓ","tj":"كُلِّ"},{"location":"2:106:18","word":"شَىْءٍۢ","qpcV2":"ﱔ","tj":"ش<rule class=ikhafa>َىۡءٍ</rule>"},{"location":"2:106:19","word":"قَدِيرٌ ١٠٦","qpcV2":"ﱕ ﱖ","tj":"<rule class=ikhafa>ق</rule>َد<rule class=madda_permissible>ِي</rule>رٌ"},{"location":"2:107:1","word":"أَلَمْ","qpcV2":"ﱗ","tj":"أَلَمۡ"},{"location":"2:107:2","word":"تَعْلَمْ","qpcV2":"ﱘ","tj":"تَعۡلَمۡ"},{"location":"2:107:3","word":"أَنَّ","qpcV2":"ﱙ","tj":"أَ<rule class=ghunnah>نّ</rule>َ"},{"location":"2:107:4","word":"ٱللَّهَ","qpcV2":"ﱚ","tj":"<rule class=ham_wasl>ٱ</rule>للَّهَ"},{"location":"2:107:5","word":"لَهُۥ","qpcV2":"ﱛ","tj":"لَهُ<rule class=madda_normal>ۥ</rule>"}]},{"line":3,"type":"text","text":"مُلْكُ ٱلسَّمَـٰوَٰتِ وَٱلْأَرْضِ ۗ وَمَا لَكُم مِّن دُونِ ٱللَّهِ مِن","verseRange":"2:107-2:107","words":[{"location":"2:107:6","word":"مُلْكُ","qpcV2":"ﱜ","tj":"مُلۡكُ"},{"location":"2:107:7","word":"ٱلسَّمَـٰوَٰتِ","qpcV2":"ﱝ","tj":"<rule class=ham_wasl>ٱ</rule><rule class=laam_shamsiyah>ل</rule>سَّمَ<rule class=madda_normal>ـٰ</rule>و<rule class=madda_normal><rule class=custom-alef-maksora>ٰ</rule></rule>تِ"},{"location":"2:107:8","word":"وَٱلْأَرْضِ ۗ","qpcV2":"ﱞﱟ","tj":"وَ<rule class=ham_wasl>ٱ</rule>لۡأَرۡضِ‌ۗ"},{"location":"2:107:9","word":"وَمَا","qpcV2":"ﱠ","tj":"وَمَا"},{"location":"2:107:10","word":"لَكُم","qpcV2":"ﱡ","tj":"لَك<rule class=idgham_shafawi>ُم</rule>"},{"location":"2:107:11","word":"مِّن","qpcV2":"ﱢ","tj":"<rule class=idgham_shafawi>م</rule>ِّ<rule class=ikhafa>ن</rule>"},{"location":"2:107:12","word":"دُونِ","qpcV2":"ﱣ","tj":"<rule class=ikhafa>د</rule>ُونِ"},{"location":"2:107:13","word":"ٱللَّهِ","qpcV2":"ﱤ","tj":"<rule class=ham_wasl>ٱ</rule>للَّهِ"},{"location":"2:107:14","word":"مِن","qpcV2":"ﱥ","tj":"م<rule class=idgham_ghunnah>ِن</rule>"}]},{"line":4,"type":"text","text":"وَلِىٍّۢ وَلَا نَصِيرٍ ١٠٧ أَمْ تُرِيدُونَ أَن تَسْـَٔلُوا۟ رَسُولَكُمْ","verseRange":"2:107-2:108","words":[{"location":"2:107:15","word":"وَلِىٍّۢ","qpcV2":"ﱦ","tj":"<rule class=idgham_ghunnah>و</rule>َلِ<rule class=idgham_ghunnah>ىٍّ</rule>"},{"location":"2:107:16","word":"وَلَا","qpcV2":"ﱧ","tj":"<rule class=idgham_ghunnah>و</rule>َلَا"},{"location":"2:107:17","word":"نَصِيرٍ ١٠٧","qpcV2":"ﱨ ﱩ","tj":"نَص<rule class=madda_permissible>ِي</rule>رٍ"},{"location":"2:108:1","word":"أَمْ","qpcV2":"ﱪ","tj":"أَمۡ"},{"location":"2:108:2","word":"تُرِيدُونَ","qpcV2":"ﱫ","tj":"تُرِيدُونَ"},{"location":"2:108:3","word":"أَن","qpcV2":"ﱬ","tj":"أَ<rule class=ikhafa>ن</rule>"},{"location":"2:108:4","word":"تَسْـَٔلُوا۟","qpcV2":"ﱭ","tj":"<rule class=ikhafa>ت</rule>َسۡــَٔلُو<rule class=slnt>اۡ</rule>"},{"location":"2:108:5","word":"رَسُولَكُمْ","qpcV2":"ﱮ","tj":"رَسُولَكُمۡ"}]},{"line":5,"type":"text","text":"كَمَا سُئِلَ مُوسَىٰ مِن قَبْلُ ۗ وَمَن يَتَبَدَّلِ ٱلْكُفْرَ بِٱلْإِيمَـٰنِ","verseRange":"2:108-2:108","words":[{"location":"2:108:6","word":"كَمَا","qpcV2":"ﱯ","tj":"كَمَا"},{"location":"2:108:7","word":"سُئِلَ","qpcV2":"ﱰ","tj":"سُئِلَ"},{"location":"2:108:8","word":"مُوسَىٰ","qpcV2":"ﱱ","tj":"مُوسَىٰ"},{"location":"2:108:9","word":"مِن","qpcV2":"ﱲ","tj":"مِ<rule class=ikhafa>ن</rule>"},{"location":"2:108:10","word":"قَبْلُ ۗ","qpcV2":"ﱳﱴ","tj":"<rule class=ikhafa>ق</rule>َ<rule class=qalaqah>بۡ</rule>لُ‌ۗ"},{"location":"2:108:11","word":"وَمَن","qpcV2":"ﱵ","tj":"وَم<rule class=idgham_ghunnah>َن</rule>"},{"location":"2:108:12","word":"يَتَبَدَّلِ","qpcV2":"ﱶ","tj":"<rule class=idgham_ghunnah>ي</rule>َتَبَدَّلِ"},{"location":"2:108:13","word":"ٱلْكُفْرَ","qpcV2":"ﱷ","tj":"<rule class=ham_wasl>ٱ</rule>لۡكُفۡرَ"},{"location":"2:108:14","word":"بِٱلْإِيمَـٰنِ","qpcV2":"ﱸ","tj":"بِ<rule class=ham_wasl>ٱ</rule>لۡإِيمَ<rule class=madda_normal>ـٰ</rule>نِ"}]},{"line":6,"type":"text","text":"فَقَدْ ضَلَّ سَوَآءَ ٱلسَّبِيلِ ١٠٨ وَدَّ كَثِيرٌۭ مِّنْ أَهْلِ","verseRange":"2:108-2:109","words":[{"location":"2:108:15","word":"فَقَدْ","qpcV2":"ﱹ","tj":"فَقَ<rule class=qalaqah>دۡ</rule>"},{"location":"2:108:16","word":"ضَلَّ","qpcV2":"ﱺ","tj":"ضَلَّ"},{"location":"2:108:17","word":"سَوَآءَ","qpcV2":"ﱻ","tj":"سَو<rule class=madda_obligatory_mottasel>َا</rule>ٓءَ"},{"location":"2:108:18","word":"ٱلسَّبِيلِ ١٠٨","qpcV2":"ﱼ ﱽ","tj":"<rule class=ham_wasl>ٱ</rule><rule class=laam_shamsiyah>ل</rule>سَّب<rule class=madda_permissible>ِي</rule>لِ"},{"location":"2:109:1","word":"وَدَّ","qpcV2":"ﱾ","tj":"وَدَّ"},{"location":"2:109:2","word":"كَثِيرٌۭ","qpcV2":"ﱿ","tj":"كَثِي<rule class=idgham_ghunnah>رٌ</rule>"},{"location":"2:109:3","word":"مِّنْ","qpcV2":"ﲀ","tj":"<rule class=idgham_ghunnah>م</rule>ِّنۡ"},{"location":"2:109:4","word":"أَهْلِ","qpcV2":"ﲁ","tj":"أَهۡلِ"}]},{"line":7,"type":"text","text":"ٱلْكِتَـٰبِ لَوْ يَرُدُّونَكُم مِّنۢ بَعْدِ إِيمَـٰنِكُمْ كُفَّارًا حَسَدًۭا","verseRange":"2:109-2:109","words":[{"location":"2:109:5","word":"ٱلْكِتَـٰبِ","qpcV2":"ﲂ","tj":"<rule class=ham_wasl>ٱ</rule>لۡكِتَ<rule class=madda_normal>ـٰ</rule>بِ"},{"location":"2:109:6","word":"لَوْ","qpcV2":"ﲃ","tj":"لَوۡ"},{"location":"2:109:7","word":"يَرُدُّونَكُم","qpcV2":"ﲄ","tj":"يَرُدُّونَك<rule class=idgham_shafawi>ُم</rule>"},{"location":"2:109:8","word":"مِّنۢ","qpcV2":"ﲅ","tj":"<rule class=idgham_shafawi>م</rule>ّ<rule class=iqlab>ِنۢ</rule>"},{"location":"2:109:9","word":"بَعْدِ","qpcV2":"ﲆ","tj":"<rule class=iqlab>ب</rule>َعۡدِ"},{"location":"2:109:10","word":"إِيمَـٰنِكُمْ","qpcV2":"ﲇ","tj":"إِيمَ<rule class=madda_normal>ـٰ</rule>نِكُمۡ"},{"location":"2:109:11","word":"كُفَّارًا","qpcV2":"ﲈ","tj":"كُفَّارًا"},{"location":"2:109:12","word":"حَسَدًۭا","qpcV2":"ﲉ","tj":"حَسَ<rule class=idgham_ghunnah>دًا</rule>"}]},{"line":8,"type":"text","text":"مِّنْ عِندِ أَنفُسِهِم مِّنۢ بَعْدِ مَا تَبَيَّنَ لَهُمُ ٱلْحَقُّ ۖ فَٱعْفُوا۟","verseRange":"2:109-2:109","words":[{"location":"2:109:13","word":"مِّنْ","qpcV2":"ﲊ","tj":"<rule class=idgham_ghunnah>م</rule>ِّنۡ"},{"location":"2:109:14","word":"عِندِ","qpcV2":"ﲋ","tj":"عِ<rule class=ikhafa>ند</rule>ِ"},{"location":"2:109:15","word":"أَنفُسِهِم","qpcV2":"ﲌ","tj":"أَ<rule class=ikhafa>نف</rule>ُسِه<rule class=idgham_shafawi>ِم</rule>"},{"location":"2:109:16","word":"مِّنۢ","qpcV2":"ﲍ","tj":"<rule class=idgham_shafawi>م</rule>ّ<rule class=iqlab>ِنۢ</rule>"},{"location":"2:109:17","word":"بَعْدِ","qpcV2":"ﲎ","tj":"<rule class=iqlab>ب</rule>َعۡدِ"},{"location":"2:109:18","word":"مَا","qpcV2":"ﲏ","tj":"مَا"},{"location":"2:109:19","word":"تَبَيَّنَ","qpcV2":"ﲐ","tj":"تَبَيَّنَ"},{"location":"2:109:20","word":"لَهُمُ","qpcV2":"ﲑ","tj":"لَهُمُ"},{"location":"2:109:21","word":"ٱلْحَقُّ ۖ","qpcV2":"ﲒﲓ","tj":"<rule class=ham_wasl>ٱ</rule>لۡحَقُّ‌ۖ"},{"location":"2:109:22","word":"فَٱعْفُوا۟","qpcV2":"ﲔ","tj":"فَ<rule class=ham_wasl>ٱ</rule>عۡفُو<rule class=slnt>اۡ</rule>"}]},{"line":9,"type":"text","text":"وَٱصْفَحُوا۟ حَتَّىٰ يَأْتِىَ ٱللَّهُ بِأَمْرِهِۦٓ ۗ إِنَّ ٱللَّهَ عَلَىٰ كُلِّ شَىْءٍۢ قَدِيرٌۭ ١٠٩","verseRange":"2:109-2:109","words":[{"location":"2:109:23","word":"وَٱصْفَحُوا۟","qpcV2":"ﲕ","tj":"وَ<rule class=ham_wasl>ٱ</rule>صۡفَحُو<rule class=slnt>اۡ</rule>"},{"location":"2:109:24","word":"حَتَّىٰ","qpcV2":"ﲖ","tj":"حَتَّىٰ"},{"location":"2:109:25","word":"يَأْتِىَ","qpcV2":"ﲗ","tj":"يَأۡتِىَ"},{"location":"2:109:26","word":"ٱللَّهُ","qpcV2":"ﲘ","tj":"<rule class=ham_wasl>ٱ</rule>للَّهُ"},{"location":"2:109:27","word":"بِأَمْرِهِۦٓ ۗ","qpcV2":"ﲙﲚ","tj":"بِأَمۡرِه<rule class=madda_obligatory_monfasel>ِۦٓ‌ۗ</rule>"},{"location":"2:109:28","word":"إِنَّ","qpcV2":"ﲛ","tj":"إِ<rule class=ghunnah>نّ</rule>َ"},{"location":"2:109:29","word":"ٱللَّهَ","qpcV2":"ﲜ","tj":"<rule class=ham_wasl>ٱ</rule>للَّهَ"},{"location":"2:109:30","word":"عَلَىٰ","qpcV2":"ﲝ","tj":"عَلَىٰ"},{"location":"2:109:31","word":"كُلِّ","qpcV2":"ﲞ","tj":"كُلِّ"},{"location":"2:109:32","word":"شَىْءٍۢ","qpcV2":"ﲟ","tj":"ش<rule class=ikhafa>َىۡءٍ</rule>"},{"location":"2:109:33","word":"قَدِيرٌۭ ١٠٩","qpcV2":"ﲠ ﲡ","tj":"<rule class=ikhafa>ق</rule>َد<rule class=madda_permissible>ِي</rule>رٌ"}]},{"line":10,"type":"text","text":"وَأَقِيمُوا۟ ٱلصَّلَوٰةَ وَءَاتُوا۟ ٱلزَّكَوٰةَ ۚ وَمَا تُقَدِّمُوا۟ لِأَنفُسِكُم","verseRange":"2:110-2:110","words":[{"location":"2:110:1","word":"وَأَقِيمُوا۟","qpcV2":"ﲢ","tj":"وَأَقِيمُو<rule class=slnt>اۡ</rule>"},{"location":"2:110:2","word":"ٱلصَّلَوٰةَ","qpcV2":"ﲣ","tj":"<rule class=ham_wasl>ٱ</rule><rule class=laam_shamsiyah>ل</rule>صَّلَ<rule class=slnt>و</rule><rule class=madda_normal>ٰ</rule>ةَ"},{"location":"2:110:3","word":"وَءَاتُوا۟","qpcV2":"ﲤ","tj":"وَءَاتُو<rule class=slnt>اۡ</rule>"},{"location":"2:110:4","word":"ٱلزَّكَوٰةَ ۚ","qpcV2":"ﲥﲦ","tj":"<rule class=ham_wasl>ٱ</rule><rule class=laam_shamsiyah>ل</rule>زَّكَ<rule class=slnt>و</rule><rule class=madda_normal>ٰ</rule>ةَ‌ۚ"},{"location":"2:110:5","word":"وَمَا","qpcV2":"ﲧ","tj":"وَمَا"},{"location":"2:110:6","word":"تُقَدِّمُوا۟","qpcV2":"ﲨ","tj":"تُقَدِّمُو<rule class=slnt>اۡ</rule>"},{"location":"2:110:7","word":"لِأَنفُسِكُم","qpcV2":"ﲩ","tj":"لِأَ<rule class=ikhafa>نف</rule>ُسِك<rule class=idgham_shafawi>ُم</rule>"}]},{"line":11,"type":"text","text":"مِّنْ خَيْرٍۢ تَجِدُوهُ عِندَ ٱللَّهِ ۗ إِنَّ ٱللَّهَ بِمَا تَعْمَلُونَ بَصِيرٌۭ ١١٠","verseRange":"2:110-2:110","words":[{"location":"2:110:8","word":"مِّنْ","qpcV2":"ﲪ","tj":"<rule class=idgham_shafawi>م</rule>ِّنۡ"},{"location":"2:110:9","word":"خَيْرٍۢ","qpcV2":"ﲫ","tj":"خَيۡ<rule class=ikhafa>رٍ</rule>"},{"location":"2:110:10","word":"تَجِدُوهُ","qpcV2":"ﲬ","tj":"<rule class=ikhafa>ت</rule>َجِدُوهُ"},{"location":"2:110:11","word":"عِندَ","qpcV2":"ﲭ","tj":"عِ<rule class=ikhafa>ند</rule>َ"},{"location":"2:110:12","word":"ٱللَّهِ ۗ","qpcV2":"ﲮﲯ","tj":"<rule class=ham_wasl>ٱ</rule>للَّهِ‌ۗ"},{"location":"2:110:13","word":"إِنَّ","qpcV2":"ﲰ","tj":"إِ<rule class=ghunnah>نّ</rule>َ"},{"location":"2:110:14","word":"ٱللَّهَ","qpcV2":"ﲱ","tj":"<rule class=ham_wasl>ٱ</rule>للَّهَ"},{"location":"2:110:15","word":"بِمَا","qpcV2":"ﲲ","tj":"بِمَا"},{"location":"2:110:16","word":"تَعْمَلُونَ","qpcV2":"ﲳ","tj":"تَعۡمَلُونَ"},{"location":"2:110:17","word":"بَصِيرٌۭ ١١٠","qpcV2":"ﲴ ﲵ","tj":"بَص<rule class=madda_permissible>ِي</rule>رٌ"}]},{"line":12,"type":"text","text":"وَقَالُوا۟ لَن يَدْخُلَ ٱلْجَنَّةَ إِلَّا مَن كَانَ هُودًا أَوْ نَصَـٰرَىٰ ۗ","verseRange":"2:111-2:111","words":[{"location":"2:111:1","word":"وَقَالُوا۟","qpcV2":"ﲶ","tj":"وَقَالُو<rule class=slnt>اۡ</rule>"},{"location":"2:111:2","word":"لَن","qpcV2":"ﲷ","tj":"ل<rule class=idgham_ghunnah>َن</rule>"},{"location":"2:111:3","word":"يَدْخُلَ","qpcV2":"ﲸ","tj":"<rule class=idgham_ghunnah>ي</rule>َ<rule class=qalaqah>دۡ</rule>خُلَ"},{"location":"2:111:4","word":"ٱلْجَنَّةَ","qpcV2":"ﲹ","tj":"<rule class=ham_wasl>ٱ</rule>لۡجَ<rule class=ghunnah>نّ</rule>َةَ"},{"location":"2:111:5","word":"إِلَّا","qpcV2":"ﲺ","tj":"إِلَّا"},{"location":"2:111:6","word":"مَن","qpcV2":"ﲻ","tj":"مَ<rule class=ikhafa>ن</rule>"},{"location":"2:111:7","word":"كَانَ","qpcV2":"ﲼ","tj":"<rule class=ikhafa>ك</rule>َانَ"},{"location":"2:111:8","word":"هُودًا","qpcV2":"ﲽ","tj":"هُودًا"},{"location":"2:111:9","word":"أَوْ","qpcV2":"ﲾ","tj":"أَوۡ"},{"location":"2:111:10","word":"نَصَـٰرَىٰ ۗ","qpcV2":"ﲿﳀ","tj":"نَصَ<rule class=madda_normal>ـٰ</rule>رَىٰ‌ۗ"}]},{"line":13,"type":"text","text":"تِلْكَ أَمَانِيُّهُمْ ۗ قُلْ هَاتُوا۟ بُرْهَـٰنَكُمْ إِن كُنتُمْ","verseRange":"2:111-2:111","words":[{"location":"2:111:11","word":"تِلْكَ","qpcV2":"ﳁ","tj":"تِلۡكَ"},{"location":"2:111:12","word":"أَمَانِيُّهُمْ ۗ","qpcV2":"ﳂﳃ","tj":"أَمَانِيُّهُمۡ‌ۗ"},{"location":"2:111:13","word":"قُلْ","qpcV2":"ﳄ","tj":"قُلۡ"},{"location":"2:111:14","word":"هَاتُوا۟","qpcV2":"ﳅ","tj":"هَاتُو<rule class=slnt>اۡ</rule>"},{"location":"2:111:15","word":"بُرْهَـٰنَكُمْ","qpcV2":"ﳆ","tj":"بُرۡهَ<rule class=madda_normal>ـٰ</rule>نَكُمۡ"},{"location":"2:111:16","word":"إِن","qpcV2":"ﳇ","tj":"إِ<rule class=ikhafa>ن</rule>"},{"location":"2:111:17","word":"كُنتُمْ","qpcV2":"ﳈ","tj":"<rule class=ikhafa>ك</rule>ُ<rule class=ikhafa>نت</rule>ُمۡ"}]},{"line":14,"type":"text","text":"صَـٰدِقِينَ ١١١ بَلَىٰ مَنْ أَسْلَمَ وَجْهَهُۥ لِلَّهِ وَهُوَ مُحْسِنٌۭ","verseRange":"2:111-2:112","words":[{"location":"2:111:18","word":"صَـٰدِقِينَ ١١١","qpcV2":"ﳉ ﳊ","tj":"صَ<rule class=madda_normal>ـٰ</rule>دِق<rule class=madda_permissible>ِي</rule>نَ"},{"location":"2:112:1","word":"بَلَىٰ","qpcV2":"ﳋﳌ","tj":"بَلَىٰ"},{"location":"2:112:2","word":"مَنْ","qpcV2":"ﳍ","tj":"مَنۡ"},{"location":"2:112:3","word":"أَسْلَمَ","qpcV2":"ﳎ","tj":"أَسۡلَمَ"},{"location":"2:112:4","word":"وَجْهَهُۥ","qpcV2":"ﳏ","tj":"وَ<rule class=qalaqah>جۡ</rule>هَهُ<rule class=madda_normal>ۥ</rule>"},{"location":"2:112:5","word":"لِلَّهِ","qpcV2":"ﳐ","tj":"لِلَّهِ"},{"location":"2:112:6","word":"وَهُوَ","qpcV2":"ﳑ","tj":"وَهُوَ"},{"location":"2:112:7","word":"مُحْسِنٌۭ","qpcV2":"ﳒ","tj":"مُحۡسِ<rule class=ikhafa>نٌ</rule>"}]},{"line":15,"type":"text","text":"فَلَهُۥٓ أَجْرُهُۥ عِندَ رَبِّهِۦ وَلَا خَوْفٌ عَلَيْهِمْ وَلَا هُمْ يَحْزَنُونَ ١١٢","verseRange":"2:112-2:112","words":[{"location":"2:112:8","word":"فَلَهُۥٓ","qpcV2":"ﳓ","tj":"<rule class=ikhafa>ف</rule>َلَهُ<rule class=madda_obligatory_monfasel>ۥٓ</rule>"},{"location":"2:112:9","word":"أَجْرُهُۥ","qpcV2":"ﳔ","tj":"أَ<rule class=qalaqah>جۡ</rule>رُهُ<rule class=madda_normal>ۥ</rule>"},{"location":"2:112:10","word":"عِندَ","qpcV2":"ﳕ","tj":"عِ<rule class=ikhafa>ند</rule>َ"},{"location":"2:112:11","word":"رَبِّهِۦ","qpcV2":"ﳖ","tj":"رَبِّه<rule class=madda_normal>ِۦ</rule>"},{"location":"2:112:12","word":"وَلَا","qpcV2":"ﳗ","tj":"وَلَا"},{"location":"2:112:13","word":"خَوْفٌ","qpcV2":"ﳘ","tj":"خَوۡفٌ"},{"location":"2:112:14","word":"عَلَيْهِمْ","qpcV2":"ﳙ","tj":"عَلَيۡهِمۡ"},{"location":"2:112:15","word":"وَلَا","qpcV2":"ﳚ","tj":"وَلَا"},{"location":"2:112:16","word":"هُمْ","qpcV2":"ﳛ","tj":"هُمۡ"},{"location":"2:112:17","word":"يَحْزَنُونَ ١١٢","qpcV2":"ﳜ ﳝ","tj":"يَحۡزَن<rule class=madda_permissible>ُو</rule>نَ"}]}]}