{
  "id": "hisn-234",
  "title": "Saying Allahu Akbar when passing the Black Stone",
  "source": "Hisn al-Muslim 234",
  "arabic": "طَافَ النَّبيُّ صلى الله عليه وسلم بِالْبَيْتِ عَلَى بَعِيرٍ كُلَّمَا أَتَى الرُّكْنَ أَشَارَ إِلَيْهِ بِشَيْءٍ عِنْدَهُ وَكَبَّرَ",
  "meaning": "The Prophet circled the KaAAbah on a camel, every time he reached the black stone he would point to it with his staff and say: (Allah is the greatest",
  "words": [
    "طَافَ",
    "النَّبيُّ",
    "صلى",
    "الله",
    "عليه",
    "وسلم",
    "بِالْبَيْتِ",
    "عَلَى",
    "بَعِيرٍ",
    "كُلَّمَا",
    "أَتَى",
    "الرُّكْنَ",
    "أَشَارَ",
    "إِلَيْهِ",
    "بِشَيْءٍ",
    "عِنْدَهُ",
    "وَكَبَّرَ"
  ],
  "phonemes": [
    "طَ",
    "اااا",
    "ف",
    "ءَ",
    "ننننَ",
    "يي",
    "ص",
    "ل",
    "ا",
    "ءَ",
    "لل",
    "ه",
    "ع",
    "ل",
    "ي",
    "ه",
    "و",
    "س",
    "ل",
    "م",
    "بِ",
    "ل",
    "بَ",
    "ييي",
    "ت",
    "عَ",
    "لَ",
    "اا",
    "بَ",
    "عِ",
    "ۦۦۦۦ",
    "ر",
    "كُ",
    "للَ",
    "مَ",
    "اا",
    "ءَ",
    "تَ",
    "اا",
    "ءَ",
    "ررُ",
    "ك",
    "ن",
    "ءَ",
    "شَ",
    "اااا",
    "ر",
    "ءِ",
    "لَ",
    "ييي",
    "ه",
    "بِ",
    "شَ",
    "ييي",
    "ء",
    "عِ",
    "ن",
    "دَ",
    "ه",
    "وَ",
    "كَ",
    "ببَ",
    "ر"
  ],
  "phonemeToWord": [
    0,
    0,
    0,
    1,
    1,
    1,
    2,
    2,
    2,
    3,
    3,
    3,
    4,
    4,
    4,
    4,
    5,
    5,
    5,
    5,
    6,
    6,
    6,
    6,
    6,
    7,
    7,
    7,
    8,
    8,
    8,
    8,
    9,
    9,
    9,
    9,
    10,
    10,
    10,
    11,
    11,
    11,
    11,
    12,
    12,
    12,
    12,
    13,
    13,
    13,
    13,
    14,
    14,
    14,
    14,
    15,
    15,
    15,
    15,
    16,
    16,
    16,
    16
  ],
  "ayahBoundaries": [
    0
  ]
}